[
    {
        "id": 138091311,
        "name": "Mới Đến Cotton Nam Không Làm Ướt Tã Quần Tã Người Lớn Có Thể Giặt Tã Vải Cũ Urineincontinence Chống Nước Tã",
        "url_key": "moi-den-cotton-nam-khong-lam-uot-ta-quan-ta-nguoi-lon-co-the-giat-ta-vai-cu-urineincontinence-chong-nuoc-ta-p138091311",
        "price": 956340,
        "description": "giới tính:Nam trọng lượng phù hợp:> 15 kg nguồn gốc:CN (Nguồn Gốc) Tuổi Phạm vi:12 + Y Số mô hình:Những Người Khác phân loại:LABS quần Loại sản phẩm:Nappies Số lượng:--- Chất liệu:cotton Age Group:Adults Diaper Type:Cloth Place of Origin:Guangdong, China (Mainland) is_customized:Yes Giá sản phẩm trên Tiki đã bao gồm thuế theo luật hiện hành. Bên cạnh đó, tuỳ vào loại sản phẩm, hình thức và địa chỉ giao hàng mà có thể phát sinh thêm chi phí khác như phí vận chuyển, phụ phí hàng cồng kềnh, thuế nhập khẩu (đối với đơn hàng giao từ nước ngoài có giá trị trên 1 triệu đồng).....",
        "images_url": [
            "https://salt.tikicdn.com/ts/product/bc/3e/6d/5cb6b9c67c7cdcd578aef9897d4a3965.jpg",
            "https://salt.tikicdn.com/ts/product/b0/60/df/85b7f65f6576471abb99943cde36952c.jpg",
            "https://salt.tikicdn.com/ts/product/22/f5/45/0b31dee3fb5835d85c92811e081f0f70.jpg",
            "https://salt.tikicdn.com/ts/product/4e/6b/be/f46f4e0fbeb49923c7a5cb021420e18c.jpg",
            "https://salt.tikicdn.com/ts/product/25/de/92/361bcc4082c2b96eb8f8f5680f01407b.jpg",
            "https://salt.tikicdn.com/ts/product/b3/db/43/600b6ab7286e2f41bd09b696029ab9be.jpg"
        ]
    },
    {
        "id": 132955835,
        "name": "Tã Người Lớn Váy Cho Người Già Và Vô Hiệu Hóa Kích Thước Lớn Chống Nước Tiểu Tiện Miếng Lót Có Thể Giặt Mama Vải Tấm Lót Ngủ Miếng Lót",
        "url_key": "ta-nguoi-lon-vay-cho-nguoi-gia-va-vo-hieu-hoa-kich-thuoc-lon-chong-nuoc-tieu-tien-mieng-lot-co-the-giat-mama-vai-tam-lot-ngu-mieng-lot-p132955835",
        "price": 894516,
        "description": "giới tính:Unisex nguồn gốc:CN (Nguồn Gốc) Tuổi Phạm vi:7-12y Tuổi Phạm vi:12 + Y Số mô hình:GP2688 Số lượng:1 Loại sản phẩm:Changing Pads & Covers Chất liệu:waterproof Kích thước:To M size:65cm L size:75cm Extra large Size:80cm Giá sản phẩm trên Tiki đã bao gồm thuế theo luật hiện hành. Bên cạnh đó, tuỳ vào loại sản phẩm, hình thức và địa chỉ giao hàng mà có thể phát sinh thêm chi phí khác như phí vận chuyển, phụ phí hàng cồng kềnh, thuế nhập khẩu (đối với đơn hàng giao từ nước ngoài có giá trị trên 1 triệu đồng).....",
        "images_url": [
            "https://salt.tikicdn.com/ts/product/be/db/90/76fc4f52462798a0197281c12ab56ef6.jpg",
            "https://salt.tikicdn.com/ts/product/40/72/51/3c99925ac0b0bac54b927fe37a500bee.jpg",
            "https://salt.tikicdn.com/ts/product/55/e5/ef/2d2213bc7f3674da55503ae32ac5410f.jpg",
            "https://salt.tikicdn.com/ts/product/4d/77/7c/a399807676d7c96917348819cf8efbfa.jpg",
            "https://salt.tikicdn.com/ts/product/1c/cb/01/97aab96838a7af30ae75d2ee4421aa58.jpg",
            "https://salt.tikicdn.com/ts/product/4c/9d/e2/b7497d3930ef0f061c75e7c109d53bbe.jpg"
        ]
    },
    {
        "id": 138085599,
        "name": "1 Chiếc Ddlg Người Lớn Tã Cho Bé Thoáng Mát Ngoài Spaceman Tã Người Lớn ABDL Bebe Tã Bố Cô Gái Bebe Giá Rẻ Vũ Trụ Không Gian đầm M/L",
        "url_key": "1-chiec-ddlg-nguoi-lon-ta-cho-be-thoang-mat-ngoai-spaceman-ta-nguoi-lon-abdl-bebe-ta-bo-co-gai-bebe-gia-re-vu-tru-khong-gian-dam-m-l-p138085599",
        "price": 482517,
        "description": "Nhóm tuổi:0-6M Nhóm tuổi:7-12M Nhóm tuổi:13-24M Nhóm tuổi:25-36M Nhóm tuổi:3-6y Nhóm tuổi:7-12y Nhóm tuổi:12 + Y nguồn gốc:CN (Nguồn Gốc) Đơn vị Đếm:1 giới tính:Unisex Tuổi Phạm vi:MATERNITY Tuổi Phạm vi:0-6M Tuổi Phạm vi:7-12M Tuổi Phạm vi:13-24M Tuổi Phạm vi:25-36M Tuổi Phạm vi:4-6y Tuổi Phạm vi:7-12y Tuổi Phạm vi:12 + Y size:L pack:1PCS Feature:Adult diapers Suitable:Unisex Feature1:abdl Feature2:DDLG Giá sản phẩm trên Tiki đã bao gồm thuế theo luật hiện hành. Bên cạnh đó, tuỳ vào loại sản phẩm, hình thức và địa chỉ giao hàng mà có thể phát sinh thêm chi phí khác như phí vận chuyển, phụ phí hàng cồng kềnh, thuế nhập khẩu (đối với đơn hàng giao từ nước ngoài có giá trị trên 1 triệu đồng).....",
        "images_url": [
            "https://salt.tikicdn.com/ts/product/9e/9a/fb/670677230635e1fdf7d64cfed15c7cb9.png",
            "https://salt.tikicdn.com/ts/product/fd/b8/c2/3396b17a1947c39389a8ec06d3223bf9.png",
            "https://salt.tikicdn.com/ts/product/b5/98/5f/fa8d4eab83384304577696e1435df3f3.jpg",
            "https://salt.tikicdn.com/ts/product/d5/f2/5b/66ae484aa0fe4c841ee1cc5f73fad2c8.png",
            "https://salt.tikicdn.com/ts/product/1b/da/ff/46450bda337d7e25d411b0036b61b7a9.png"
        ]
    },
    {
        "id": 132913107,
        "name": "ABDL Tã Người Lớn Pvc Có Thể Tái Sử Dụng Cho Bé Quần Tã Onesize Nhựa Bikini DDLG Người Lớn Bé Mới Quần Lót Xanh Dương Tã",
        "url_key": "abdl-ta-nguoi-lon-pvc-co-the-tai-su-dung-cho-be-quan-ta-onesize-nhua-bikini-ddlg-nguoi-lon-be-moi-quan-lot-xanh-duong-ta-p132913107",
        "price": 420693,
        "description": "nguồn gốc:CN (Nguồn Gốc) mùa:Bốn mùa Tuổi Phạm vi:7-12y Tuổi Phạm vi:12 + Y Chất liệu:Polyester Loại sản phẩm:leggings giới tính:WOMEN Loại mô hình:Rắn Tên bộ phận:Thai sản Giá sản phẩm trên Tiki đã bao gồm thuế theo luật hiện hành. Bên cạnh đó, tuỳ vào loại sản phẩm, hình thức và địa chỉ giao hàng mà có thể phát sinh thêm chi phí khác như phí vận chuyển, phụ phí hàng cồng kềnh, thuế nhập khẩu (đối với đơn hàng giao từ nước ngoài có giá trị trên 1 triệu đồng).....",
        "images_url": [
            "https://salt.tikicdn.com/ts/product/ac/c3/91/13c4547632458b0d29001b9d0ab3fd1e.jpg",
            "https://salt.tikicdn.com/ts/product/da/35/1f/14e13ef6e47c3bd88c36bf9c478baf3f.jpg",
            "https://salt.tikicdn.com/ts/product/dc/fa/dd/bf9de547d3dea58a78e4ad9a12373e65.jpg",
            "https://salt.tikicdn.com/ts/product/bd/b6/e6/167c1a8dc5110160e97935e4a5e02c89.jpg",
            "https://salt.tikicdn.com/ts/product/95/0b/38/2531c2ebed4dc47a3abbf5c40e20ef75.jpg",
            "https://salt.tikicdn.com/ts/product/2c/38/97/d9f95fadce40c515bdbe17f1fe337e82.jpg"
        ]
    },
    {
        "id": 138086793,
        "name": "Tã Quần Người Lớn Nước Tiểu Bộ Sưu Tập Túi Có Thể Tái Sử Dụng Ốp BồN TiểU Nam Người Cao Tuổi Nằm Liệt GiườNg BệNh Nhân Tã Người Lớn Tiểu Tiện",
        "url_key": "ta-quan-nguoi-lon-nuoc-tieu-bo-suu-tap-tui-co-the-tai-su-dung-op-bon-tieu-nam-nguoi-cao-tuoi-nam-liet-giuong-benh-nhan-ta-nguoi-lon-tieu-tien-p138086793",
        "price": 573804,
        "description": "nguồn gốc:CN (Nguồn Gốc) Số mô hình:Urinal Type 1:Urine Bag Type 2:Urine Collector Use:Elderly Bedridden Patients Dropshipping/Wholesale:Support Giá sản phẩm trên Tiki đã bao gồm thuế theo luật hiện hành. Bên cạnh đó, tuỳ vào loại sản phẩm, hình thức và địa chỉ giao hàng mà có thể phát sinh thêm chi phí khác như phí vận chuyển, phụ phí hàng cồng kềnh, thuế nhập khẩu (đối với đơn hàng giao từ nước ngoài có giá trị trên 1 triệu đồng).....",
        "images_url": [
            "https://salt.tikicdn.com/ts/product/57/17/00/b401625aba4ff264ad6992eac0396745.jpg",
            "https://salt.tikicdn.com/ts/product/6c/dc/b7/aa63e66ab033ac9eb536f2a0cc371b88.jpg",
            "https://salt.tikicdn.com/ts/product/93/ae/57/5e6f3ad84c7b5fd70329526e9ec0987c.jpg",
            "https://salt.tikicdn.com/ts/product/28/96/73/03db6a3e72ce5fd7afa0ecef3324af11.jpg",
            "https://salt.tikicdn.com/ts/product/77/41/87/baa148e920e2187b544b4ea7b2361ffa.jpg",
            "https://salt.tikicdn.com/ts/product/33/bd/73/600caf59463fb33ebcc9f8485490f469.jpg"
        ]
    },
    {
        "id": 132945159,
        "name": "Có Thể Tái Sử Dụng Tã Người Lớn Cho Người Già Và Vô Hiệu Hóa Kích Thước Lớn Có Thể Điều Chỉnh TPU Áo Khoác Chống Thấm Nước Tiểu Tiện Undewear",
        "url_key": "co-the-tai-su-dung-ta-nguoi-lon-cho-nguoi-gia-va-vo-hieu-hoa-kich-thuoc-lon-co-the-dieu-chinh-tpu-ao-khoac-chong-tham-nuoc-tieu-tien-undewear-p132945159",
        "price": 690690,
        "description": "giới tính:Unisex trọng lượng phù hợp:> 15 kg nguồn gốc:CN (Nguồn Gốc) Tuổi Phạm vi:12 + Y Số mô hình:Những Người Khác phân loại:LABS quần Loại sản phẩm:Nappies Số lượng:---- Chất liệu:outer polyester ,inner fleece colour:white red pink green Absorption:Soft Breathable Age Group:Adults Diaper Type:Cloth Feature:outer white waterproof Place of Origin:Guangdong, China (Mainland) is_customized:Yes Giá sản phẩm trên Tiki đã bao gồm thuế theo luật hiện hành. Bên cạnh đó, tuỳ vào loại sản phẩm, hình thức và địa chỉ giao hàng mà có thể phát sinh thêm chi phí khác như phí vận chuyển, phụ phí hàng cồng kềnh, thuế nhập khẩu (đối với đơn hàng giao từ nước ngoài có giá trị trên 1 triệu đồng).....",
        "images_url": [
            "https://salt.tikicdn.com/ts/product/46/94/d9/1ea02e5b9c50dccae0b8b2e3ffb69490.jpg",
            "https://salt.tikicdn.com/ts/product/3b/b4/fa/a38da6e013007a985cff36991015abbc.jpg",
            "https://salt.tikicdn.com/ts/product/e9/58/b9/e83be454284032a546ea50372e1446bb.jpg",
            "https://salt.tikicdn.com/ts/product/f4/cd/05/51eb7f52963a51a3486fcda846623f3d.jpg",
            "https://salt.tikicdn.com/ts/product/78/ed/4d/feba0f76f9b4f47f60023e66d20f7c66.jpg",
            "https://salt.tikicdn.com/ts/product/6d/c6/3e/7ef760822f65a1fede15eb263050e87a.jpg"
        ]
    },
    {
        "id": 138084896,
        "name": "Có thể tái sử dụng Tã người lớn cho Người Già và Vô Hiệu Hóa Siêu Lớn Kích thước Có Thể Điều Chỉnh TPU Áo Khoác Chống Thấm Nước Tiểu Tiện Quần undewearD30",
        "url_key": "co-the-tai-su-dung-ta-nguoi-lon-cho-nguoi-gia-va-vo-hieu-hoa-sieu-lon-kich-thuoc-co-the-dieu-chinh-tpu-ao-khoac-chong-tham-nuoc-tieu-tien-quan-undeweard30-p138084896",
        "price": 447258,
        "description": "Số lượng:1pc adult diapper Chất liệu:stay dry suede cloth Loại sản phẩm:Adult Diaper trọng lượng:0.1kg kích thước:XXL Số mô hình:18DE24D30Daipper Giá sản phẩm trên Tiki đã bao gồm thuế theo luật hiện hành. Bên cạnh đó, tuỳ vào loại sản phẩm, hình thức và địa chỉ giao hàng mà có thể phát sinh thêm chi phí khác như phí vận chuyển, phụ phí hàng cồng kềnh, thuế nhập khẩu (đối với đơn hàng giao từ nước ngoài có giá trị trên 1 triệu đồng).....",
        "images_url": [
            "https://salt.tikicdn.com/ts/product/c5/f7/4b/845c70f2614731ac40a2fb99ed664960.jpg",
            "https://salt.tikicdn.com/ts/product/e2/95/3a/decfa7ed29362513919d63f120fd5321.jpg",
            "https://salt.tikicdn.com/ts/product/df/49/d4/2802ea846051cdd20de2d461abdce53b.jpg",
            "https://salt.tikicdn.com/ts/product/b3/2c/7e/8900cf99181e2b13f3c2804587653b77.jpg",
            "https://salt.tikicdn.com/ts/product/92/ab/93/cdc8e83131d3558c82792d00c21a5edd.jpg",
            "https://salt.tikicdn.com/ts/product/ba/17/7b/7493ba1d22ee74b9f0599f493995c218.jpg"
        ]
    },
    {
        "id": 132914028,
        "name": "2 Chiếc 45*60Cm Có Thể Tái Sử Dụng Tiểu Tiện Giường Lót 4 Lớp Có Thể Rửa Miếng Lót Thấm Hút Miếng Lót Cho Người Lớn Không Tự Chủ Miếng Lót bé Đái Dầm",
        "url_key": "2-chiec-45-60cm-co-the-tai-su-dung-tieu-tien-giuong-lot-4-lop-co-the-rua-mieng-lot-tham-hut-mieng-lot-cho-nguoi-lon-khong-tu-chu-mieng-lot-be-dai-dam-p132914028",
        "price": 469476,
        "description": "nguồn gốc:CN (Nguồn Gốc) Số mô hình:Adults Incontinence Pad Item Size:Approx.45 * 60cm / 17.7 * 23.6inch Giá sản phẩm trên Tiki đã bao gồm thuế theo luật hiện hành. Bên cạnh đó, tuỳ vào loại sản phẩm, hình thức và địa chỉ giao hàng mà có thể phát sinh thêm chi phí khác như phí vận chuyển, phụ phí hàng cồng kềnh, thuế nhập khẩu (đối với đơn hàng giao từ nước ngoài có giá trị trên 1 triệu đồng).....",
        "images_url": [
            "https://salt.tikicdn.com/ts/product/70/94/42/c5eb484e3067324886f707f2128c152d.jpg",
            "https://salt.tikicdn.com/ts/product/6d/f3/9e/2f952ed93229fad9462289a7a208ce15.jpg",
            "https://salt.tikicdn.com/ts/product/62/10/4f/6ecc391182364d70a0e704e448934386.jpg",
            "https://salt.tikicdn.com/ts/product/6b/0f/3e/9da5a860e79f450bbabd9b56812997d3.jpg",
            "https://salt.tikicdn.com/ts/product/6b/34/cc/2963b8df7b62edb2462845c219b164e1.jpg",
            "https://salt.tikicdn.com/ts/product/96/8f/3b/4515aca74cae7cd3147c095dda2adec9.jpg"
        ]
    },
    {
        "id": 138086093,
        "name": "Có thể tái sử dụng Tã người lớn Nam Nước Tiểu Túi Ngày Đêm Dual Sử Dụng Đeo Nam Nước Tiểu Túi Nằm Liệt Giường Bệnh Nhân Tiểu Tiện Quần",
        "url_key": "co-the-tai-su-dung-ta-nguoi-lon-nam-nuoc-tieu-tui-ngay-dem-dual-su-dung-deo-nam-nuoc-tieu-tui-nam-liet-giuong-benh-nhan-tieu-tien-quan-p138086093",
        "price": 508599,
        "description": "Số mô hình:as show Item Type:Urine Bag Material:Latex Giá sản phẩm trên Tiki đã bao gồm thuế theo luật hiện hành. Bên cạnh đó, tuỳ vào loại sản phẩm, hình thức và địa chỉ giao hàng mà có thể phát sinh thêm chi phí khác như phí vận chuyển, phụ phí hàng cồng kềnh, thuế nhập khẩu (đối với đơn hàng giao từ nước ngoài có giá trị trên 1 triệu đồng).....",
        "images_url": [
            "https://salt.tikicdn.com/ts/product/e0/17/4a/ebe972890125dbd2ab20d95041366f7f.jpg",
            "https://salt.tikicdn.com/ts/product/f1/2f/59/7d51f2f6184ab3309b148c1dc2a813e3.jpg",
            "https://salt.tikicdn.com/ts/product/b8/fa/b8/5a2f1a2fd338565313b78938136f99b3.jpg",
            "https://salt.tikicdn.com/ts/product/6f/6f/b9/0df6320dc391c8447642d755020f911e.jpg",
            "https://salt.tikicdn.com/ts/product/32/e9/71/e425a1f2f41b9ea87849bde398796a10.jpg",
            "https://salt.tikicdn.com/ts/product/6b/77/ca/2b24f700a335335f37572b894a3c0bd6.jpg"
        ]
    },
    {
        "id": 138089506,
        "name": "Tã Quần Người Lớn Chống Thấm Nước Có Thể Giặt Quần Người Cao Tuổi Chăm Sóc Có Thể Tái Sử Dụng Tã Vải Chống Rò Rỉ Lót Quần Tã Cho Nam & Nữ",
        "url_key": "ta-quan-nguoi-lon-chong-tham-nuoc-co-the-giat-quan-nguoi-cao-tuoi-cham-soc-co-the-tai-su-dung-ta-vai-chong-ro-ri-lot-quan-ta-cho-nam-nu-p138089506",
        "price": 767004,
        "description": "nguồn gốc:CN (Nguồn Gốc) Số mô hình:Washable Pants Số lượng:1pcs Chất liệu:Waterproof cloth Loại sản phẩm:Adult Diaper trọng lượng:0.2kg kích thước:XL feature:reusable soft Giá sản phẩm trên Tiki đã bao gồm thuế theo luật hiện hành. Bên cạnh đó, tuỳ vào loại sản phẩm, hình thức và địa chỉ giao hàng mà có thể phát sinh thêm chi phí khác như phí vận chuyển, phụ phí hàng cồng kềnh, thuế nhập khẩu (đối với đơn hàng giao từ nước ngoài có giá trị trên 1 triệu đồng).....",
        "images_url": [
            "https://salt.tikicdn.com/ts/product/45/ed/1a/4423bc1b3d7e352132d729efb461987e.jpg",
            "https://salt.tikicdn.com/ts/product/28/a5/d1/8039d77669a25d33ae5733675f2609d3.jpg",
            "https://salt.tikicdn.com/ts/product/79/cf/39/3f4fa8a7e806fb67069294237c78f3b0.jpg",
            "https://salt.tikicdn.com/ts/product/2a/a7/c2/f3d2b40eb058eae72bffd3a7ed9cfe23.jpg",
            "https://salt.tikicdn.com/ts/product/e3/fd/e9/c8064824971e9422266d69f4afbf854b.jpg",
            "https://salt.tikicdn.com/ts/product/4b/d0/29/d06ffaa5892e142ef10ccc4ebb71b236.jpg"
        ]
    },
    {
        "id": 132955265,
        "name": "Tã Người Yêu Và Ẻo Lả Người Lớn Bé Onesie Bộ Đồ Ngủ Chụp Đáy Quần Romper Áo Liền Quần Đùi Bé Gấu Thỏ Trưởng Thành Onesie Cho Người Lớn Trẻ Em Bé Trai",
        "url_key": "ta-nguoi-yeu-va-eo-la-nguoi-lon-be-onesie-bo-do-ngu-chup-day-quan-romper-ao-lien-quan-dui-be-gau-tho-truong-thanh-onesie-cho-nguoi-lon-tre-em-be-trai-p132955265",
        "price": 838005,
        "description": "Chất liệu:Polyester nguồn gốc:CN (Nguồn Gốc) giới tính:Unisex Loại sản phẩm:Tà vẹt chăn Fit:Phù hợp với đúng kích thước, mất bình thường của bạn kích thước Loại vải:Dạ Loại mô hình:Hình Hoạt Hình Tên bộ phận:Trẻ em Feature:Adult size Giá sản phẩm trên Tiki đã bao gồm thuế theo luật hiện hành. Bên cạnh đó, tuỳ vào loại sản phẩm, hình thức và địa chỉ giao hàng mà có thể phát sinh thêm chi phí khác như phí vận chuyển, phụ phí hàng cồng kềnh, thuế nhập khẩu (đối với đơn hàng giao từ nước ngoài có giá trị trên 1 triệu đồng).....",
        "images_url": [
            "https://salt.tikicdn.com/ts/product/f5/f5/84/e13402d931998f1b2a2535056bb3b088.jpg",
            "https://salt.tikicdn.com/ts/product/3c/91/d7/e8c291f2db03bf6d57fc9838576da700.jpg",
            "https://salt.tikicdn.com/ts/product/a8/0d/a0/752e67c7a6c52c482e02712be86fb688.jpg",
            "https://salt.tikicdn.com/ts/product/67/48/55/9e8b05994efe648c45abf6ca1fb291e7.jpg",
            "https://salt.tikicdn.com/ts/product/26/31/f5/cf79a0fa66b14283048e3cccccf08782.jpg"
        ]
    },
    {
        "id": 99627224,
        "name": "Montessori Toy Stacking Toys Silicone Educational Building Blocks Style 1",
        "url_key": "montessori-toy-stacking-toys-silicone-educational-building-blocks-style-1-p99627224",
        "price": 143000,
        "description": "Package Includes: 1 Piece Stacking Toy Note: Due to the difference between different monitors, the picture may not reflect the actual color of the item. Due to manual measurement, there may be 1-2cm error in size. Giá sản phẩm trên Tiki đã bao gồm thuế theo luật hiện hành. Bên cạnh đó, tuỳ vào loại sản phẩm, hình thức và địa chỉ giao hàng mà có thể phát sinh thêm chi phí khác như phí vận chuyển, phụ phí hàng cồng kềnh, thuế nhập khẩu (đối với đơn hàng giao từ nước ngoài có giá trị trên 1 triệu đồng).....",
        "images_url": [
            "https://salt.tikicdn.com/ts/product/ee/f0/b7/8f9885563d4422d9ac8e3d9f79b84b2e.jpg",
            "https://salt.tikicdn.com/ts/product/03/d0/4b/7a1fb9100a0407c3b403b794cf6f24b2.jpg",
            "https://salt.tikicdn.com/ts/product/07/76/7b/b3ab236f14a72164e8ee6c67fd2e2214.jpg",
            "https://salt.tikicdn.com/ts/product/d3/e2/ef/a99a9f307a61ad05a2e923b458975fda.jpg",
            "https://salt.tikicdn.com/ts/product/ba/92/a3/9820a883df86d2f1f1ff184a9f6994f7.jpg",
            "https://salt.tikicdn.com/ts/product/1d/eb/ca/8fc6ca3a265d8042f1c3c1836e91ec74.jpg",
            "https://salt.tikicdn.com/ts/product/07/76/7b/e885267086fb01a408143f35b211b89a.jpg",
            "https://salt.tikicdn.com/ts/product/88/f7/4b/ccea51b5bc6fe6db2237905aa14e6e7b.jpg",
            "https://salt.tikicdn.com/ts/product/55/a6/6f/135ba85f74fcc18ec753a1ca3f08a7a3.jpg",
            "https://salt.tikicdn.com/ts/product/39/6c/d3/129f20a5469acb424dd8dcb3c08848fe.jpg",
            "https://salt.tikicdn.com/ts/product/3c/94/26/a4a8d83c041ae7daeb9fab5d0bf02410.jpg",
            "https://salt.tikicdn.com/ts/product/3b/56/74/6cb84107e4b00c8853ab37ae5566ae6a.jpg"
        ]
    },
    {
        "id": 71928727,
        "name": "Bạch tuộc nhồi bông chuyển đổi cảm xúc . Đồ chơi cho bé an toàn thoải mái chất liệu mềm mại",
        "url_key": "bach-tuoc-nhoi-bong-chuyen-doi-cam-xuc-do-choi-cho-be-an-toan-thoai-mai-chat-lieu-mem-mai-p71928727",
        "price": 98000,
        "description": "Package Includes: 1 Piece Plush Octopus Toy Note: Color might be slightly different due to the color calibration of each individual monitor. Please allow slightly measuring deviation due to manual measurement. Giá sản phẩm trên Tiki đã bao gồm thuế theo luật hiện hành. Bên cạnh đó, tuỳ vào loại sản phẩm, hình thức và địa chỉ giao hàng mà có thể phát sinh thêm chi phí khác như phí vận chuyển, phụ phí hàng cồng kềnh, thuế nhập khẩu (đối với đơn hàng giao từ nước ngoài có giá trị trên 1 triệu đồng).....",
        "images_url": [
            "https://salt.tikicdn.com/ts/product/64/32/b8/dda15558915e00a8bf47799a2c021d5f.jpg",
            "https://salt.tikicdn.com/ts/product/35/bc/14/0a9140a81c726fc11eb672d29a07686a.jpg",
            "https://salt.tikicdn.com/ts/product/47/d6/2f/3727fa0cfacc9b1c2f09c3e6c91e1b89.jpg",
            "https://salt.tikicdn.com/ts/product/ec/1e/c3/c77f8fbb7bc0cd21e9783603ba3dbd4e.jpg",
            "https://salt.tikicdn.com/ts/product/98/87/25/e99ffba642cc4637885297940c3a12a1.jpg",
            "https://salt.tikicdn.com/ts/product/2a/ad/cb/11853432625c4dfd08e987333e930a51.jpg",
            "https://salt.tikicdn.com/ts/product/2f/2c/ff/8217738e6b0e9a8f0e1bbf9dc49899f7.jpg",
            "https://salt.tikicdn.com/ts/product/3e/55/cb/5604e4c29423e19d83d065ccaa826690.jpg",
            "https://salt.tikicdn.com/ts/product/3b/ef/7f/39670d756497ffca52b978e04faf0a00.jpg",
            "https://salt.tikicdn.com/ts/product/c9/cf/2a/45b31a6c9535cf14aad26ffa6ca779cf.jpg",
            "https://salt.tikicdn.com/ts/product/1f/ed/af/8fa6a336050b2f28d1ef50feb90d9aa5.jpg",
            "https://salt.tikicdn.com/ts/product/0c/00/74/f29527febee2f5e1a133bf0ad02860e6.jpg"
        ]
    },
    {
        "id": 184897376,
        "name": "Cosplay Hoạt Hình Pikachu Onesie Đồ Ngủ Halloween Kigurumi Đồ Ngủ Trẻ Em",
        "url_key": "cosplay-hoat-hinh-pikachu-onesie-do-ngu-halloween-kigurumi-do-ngu-tre-em-p184897376",
        "price": 333331,
        "description": "Kích thước là unisex, vì vậy bất kể bạn là nam hay nữ, bạn đều có thể mặc nó, chúng tôi cũng đề nghị bạn có thể sử dụng làm đồ ngủ cặp đôi, bạn có thể phối hợp nó, như đường may màu xanh và hồng, ma quỷ và dơi, Vân vân Có khóa kéo quanh hông, rất dễ dàng đi phòng tắm; Xin vui lòng cho tôi biết nếu bạn muốn nhiều hơn, chúng tôi sẽ cung cấp cho bạn một mức giá tốt với vận chuyển nhanh chóng!Cảm ơn! Kích thước trẻ em: 4t / 100: Vừa 88-105cm (Chiều cao) 6t / 110: Vừa 105-115cm (Chiều cao) 8t / 120: Vừa vặn 116-125cm (Chiều cao) 10t / 130: Vừa vặn 125-135cm (Chiều cao) 12t / 140: Phù hợp135-145cm (Chiều cao) So sánh kích thước chi tiết với của bạn, vui lòng cho phép chênh lệch 1-2CM do đo lường thủ công, cảm ơn Lưu ý: Do sự khác biệt giữa các màn hình khác nhau, hình ảnh có thể không phản ánh màu sắc thực tế của sản phẩm. Chúng tôi đảm bảo mẫu mã giống như trong hình, nhưng mỗi người cho kết quả khác nhau. Cảm ơn bạn! Mặt hàng Bao gồm (không bao gồm Dép) 1x đồ ngủ Giá sản phẩm trên Tiki đã bao gồm thuế theo luật hiện hành. Bên cạnh đó, tuỳ vào loại sản phẩm, hình thức và địa chỉ giao hàng mà có thể phát sinh thêm chi phí khác như phí vận chuyển, phụ phí hàng cồng kềnh, thuế nhập khẩu (đối với đơn hàng giao từ nước ngoài có giá trị trên 1 triệu đồng).....",
        "images_url": [
            "https://salt.tikicdn.com/media/catalog/product/f5/15/2228f38cf84d1b8451bb49e2c4537081.png"
        ]
    },
    {
        "id": 184940921,
        "name": "Bộ Đồ Ngủ Trẻ Em Hình Động Vật Bằng Vải Flanen Đồ Ngủ Trẻ Em Hoạt Hình Pegasus Đêm Động Vật Có Mũ Mùa Đông Cho Bé Trai Bé Gái Đồ Ngủ Một Mảnh",
        "url_key": "bo-do-ngu-tre-em-hinh-dong-vat-bang-vai-flanen-do-ngu-tre-em-hoat-hinh-pegasus-dem-dong-vat-co-mu-mua-dong-cho-be-trai-be-gai-do-ngu-mot-manh-p184940921",
        "price": 350000,
        "description": "Kích thước là unisex, vì vậy bất kể bạn là nam hay nữ, bạn đều có thể mặc nó, chúng tôi cũng đề nghị bạn có thể sử dụng làm đồ ngủ cặp đôi, bạn có thể phối hợp nó, như đường may màu xanh và hồng, ma quỷ và dơi, Vân vân Có khóa kéo quanh hông, rất dễ dàng đi phòng tắm; Xin vui lòng cho tôi biết nếu bạn muốn nhiều hơn, chúng tôi sẽ cung cấp cho bạn một mức giá tốt với vận chuyển nhanh chóng!Cảm ơn! Kích thước trẻ em: 4t / 100: Vừa 88-105cm (Chiều cao) 6t / 110: Vừa 105-115cm (Chiều cao) 8t / 120: Vừa vặn 116-125cm (Chiều cao) 10t / 130: Vừa vặn 125-135cm (Chiều cao) 12t / 140: Phù hợp135-145cm (Chiều cao) So sánh kích thước chi tiết với của bạn, vui lòng cho phép chênh lệch 1-2CM do đo lường thủ công, cảm ơn Lưu ý: Do sự khác biệt giữa các màn hình khác nhau, hình ảnh có thể không phản ánh màu sắc thực tế của sản phẩm. Chúng tôi đảm bảo mẫu mã giống như trong hình, nhưng mỗi người cho kết quả khác nhau. Cảm ơn bạn! Mặt hàng Bao gồm (không bao gồm Dép) 1x đồ ngủ Giá sản phẩm trên Tiki đã bao gồm thuế theo luật hiện hành. Bên cạnh đó, tuỳ vào loại sản phẩm, hình thức và địa chỉ giao hàng mà có thể phát sinh thêm chi phí khác như phí vận chuyển, phụ phí hàng cồng kềnh, thuế nhập khẩu (đối với đơn hàng giao từ nước ngoài có giá trị trên 1 triệu đồng).....",
        "images_url": [
            "https://salt.tikicdn.com/media/catalog/product/f5/15/2228f38cf84d1b8451bb49e2c4537081.png"
        ]
    },
    {
        "id": 184903046,
        "name": "Bộ Đồ Ngủ Gấu Trúc Mắt Đỏ Bộ Đồ Ngủ Hóa Trang Động Vật Cho Bé Trai Bé Gái Kigurumi Bộ Đồ Liền Thân Cho Trẻ Tập Đi",
        "url_key": "bo-do-ngu-gau-truc-mat-do-bo-do-ngu-hoa-trang-dong-vat-cho-be-trai-be-gai-kigurumi-bo-do-lien-than-cho-tre-tap-di-p184903046",
        "price": 333331,
        "description": "Kích thước là unisex, vì vậy bất kể bạn là nam hay nữ, bạn đều có thể mặc nó, chúng tôi cũng đề nghị bạn có thể sử dụng làm đồ ngủ cặp đôi, bạn có thể phối hợp nó, như đường may màu xanh và hồng, ma quỷ và dơi, Vân vân Có khóa kéo quanh hông, rất dễ dàng đi phòng tắm; Xin vui lòng cho tôi biết nếu bạn muốn nhiều hơn, chúng tôi sẽ cung cấp cho bạn một mức giá tốt với vận chuyển nhanh chóng!Cảm ơn! Kích thước trẻ em: 4t / 100: Vừa 88-105cm (Chiều cao) 6t / 110: Vừa 105-115cm (Chiều cao) 8t / 120: Vừa vặn 116-125cm (Chiều cao) 10t / 130: Vừa vặn 125-135cm (Chiều cao) 12t / 140: Phù hợp135-145cm (Chiều cao) So sánh kích thước chi tiết với của bạn, vui lòng cho phép chênh lệch 1-2CM do đo lường thủ công, cảm ơn Lưu ý: Do sự khác biệt giữa các màn hình khác nhau, hình ảnh có thể không phản ánh màu sắc thực tế của sản phẩm. Chúng tôi đảm bảo mẫu mã giống như trong hình, nhưng mỗi người cho kết quả khác nhau. Cảm ơn bạn! Mặt hàng Bao gồm (không bao gồm Dép) 1x đồ ngủ Giá sản phẩm trên Tiki đã bao gồm thuế theo luật hiện hành. Bên cạnh đó, tuỳ vào loại sản phẩm, hình thức và địa chỉ giao hàng mà có thể phát sinh thêm chi phí khác như phí vận chuyển, phụ phí hàng cồng kềnh, thuế nhập khẩu (đối với đơn hàng giao từ nước ngoài có giá trị trên 1 triệu đồng).....",
        "images_url": [
            "https://salt.tikicdn.com/media/catalog/product/f5/15/2228f38cf84d1b8451bb49e2c4537081.png"
        ]
    },
    {
        "id": 124402226,
        "name": "Bộ Ba Nón Khăn Tay Bộ Nón Trẻ Em Giữ Ấm Mùa Đông Mitten Pom Pom Nón Len Thu Đông Bé Gái Và Bé Trai mũ Lưỡi Trai Thời Trang Bộ Mới",
        "url_key": "bo-ba-non-khan-tay-bo-non-tre-em-giu-am-mua-dong-mitten-pom-pom-non-len-thu-dong-be-gai-va-be-trai-mu-luoi-trai-thoi-trang-bo-moi-p124402226",
        "price": 676683,
        "description": "Loại mô hình:Rắn Tên bộ phận:Adult nguồn gốc:CN (Nguồn Gốc) Chất liệu:COTTON Applicable Scene:OUTDOOR giới tính:Unisex tính năng:Giữ Ấm Mùa áp dụng:Winter Số mô hình:HCXY029 Loại sản phẩm:Skullies & Beanies phong cách:Bình thường ngày phát hành:Autumn2021 Size::for head circumference42-55cm Feature1::Keep warm Release Date::Autumn2021 Item name::Beanie Hat Colors::9 colors Feature2::Keep Warm Gender::unisex Material::Cotton Applicable Season::Winter Giá sản phẩm trên Tiki đã bao gồm thuế theo luật hiện hành. Bên cạnh đó, tuỳ vào loại sản phẩm, hình thức và địa chỉ giao hàng mà có thể phát sinh thêm chi phí khác như phí vận chuyển, phụ phí hàng cồng kềnh, thuế nhập khẩu (đối với đơn hàng giao từ nước ngoài có giá trị trên 1 triệu đồng).....",
        "images_url": [
            "https://salt.tikicdn.com/ts/product/67/36/6a/6b658f458d6da86b2b5c35bd56ec08e8.jpg",
            "https://salt.tikicdn.com/ts/product/77/42/be/c398ed06cf7f0d9f7004efe431a2964e.jpg",
            "https://salt.tikicdn.com/ts/product/e3/19/f0/0b5d7d40c33b705c342b559db4ee7f8d.jpg",
            "https://salt.tikicdn.com/ts/product/e8/df/26/80c47265e55795d0a0d7a32c9d8fe9f9.jpg",
            "https://salt.tikicdn.com/ts/product/4e/e8/c3/37eaa2fb37892f5139bbdd04132c927d.jpg",
            "https://salt.tikicdn.com/ts/product/1d/83/60/3e62a1958c1d1cb3066e168536acfa11.jpg"
        ]
    },
    {
        "id": 108486600,
        "name": "Useless Box Pointless Box Leave Me Alone Box Toys Machine Box Turns Itself Off Useless Box",
        "url_key": "useless-box-pointless-box-leave-me-alone-box-toys-machine-box-turns-itself-off-useless-box-p108486600",
        "price": 201000,
        "description": "- Size(LxWxH):Approx.15x9x7cm/5.91x3.54x2.76inch - Package Includes: - 1 Piece Useless Box - Giá sản phẩm trên Tiki đã bao gồm thuế theo luật hiện hành. Bên cạnh đó, tuỳ vào loại sản phẩm, hình thức và địa chỉ giao hàng mà có thể phát sinh thêm chi phí khác như phí vận chuyển, phụ phí hàng cồng kềnh, thuế nhập khẩu (đối với đơn hàng giao từ nước ngoài có giá trị trên 1 triệu đồng).....",
        "images_url": [
            "https://salt.tikicdn.com/ts/product/ce/69/a3/50c765a036f5e1cee1ca983583346d79.jpg",
            "https://salt.tikicdn.com/ts/product/14/ec/e4/c2992575c1583a020ed3e520759fe40a.jpg",
            "https://salt.tikicdn.com/ts/product/c3/22/86/a216588ab92ed06888d993d9cf285f9f.jpg",
            "https://salt.tikicdn.com/ts/product/fa/59/95/43b8fa62d9daec3240a863f445a67235.jpg",
            "https://salt.tikicdn.com/ts/product/18/65/cc/ecc2bce6633b1566da7b010919ff145f.jpg",
            "https://salt.tikicdn.com/ts/product/e7/2c/b9/05d4fe5a2bee496f31398f1fd3f2bae0.jpg",
            "https://salt.tikicdn.com/ts/product/4b/fd/82/6ec912a5547cf1cc9ba565406fd7e827.jpg",
            "https://salt.tikicdn.com/ts/product/24/a1/49/11bfd03f9cd7d8a092b8c33c877404fb.jpg",
            "https://salt.tikicdn.com/ts/product/66/58/ab/89b24473d7ae6a1b74e2d7c56dd3045f.jpg",
            "https://salt.tikicdn.com/ts/product/60/ae/76/2a3fc3fd7876d29e1225ae594e0a67aa.jpg",
            "https://salt.tikicdn.com/ts/product/cb/96/05/d20ac865a0072b91737d5961d02b97b2.jpg",
            "https://salt.tikicdn.com/ts/product/c7/f5/4f/77dbff4c17fc60756b13e89887e49357.jpg"
        ]
    },
    {
        "id": 124599032,
        "name": "Đồ Bơi Trẻ Em 3 Miếng Splitted Áo Tắm Bé Trai Khủng Long Thằn Lằn In Hình Trẻ Em Bơi Đồ Bơi Cho Bé Chống Tia UV",
        "url_key": "do-boi-tre-em-3-mieng-splitted-ao-tam-be-trai-khung-long-than-lan-in-hinh-tre-em-boi-do-boi-cho-be-chong-tia-uv-p124599032",
        "price": 624036,
        "description": "Chất liệu:COTTON Chất liệu:Polyester Chất liệu:NYLON Chất liệu:spandex nguồn gốc:CN (Nguồn Gốc) giới tính:Con trai Loại thể thao:Swim Số mô hình:Swimsuit Kids Fit:Phù hợp với đúng kích thước, mất bình thường của bạn kích thước Loại mô hình:Động vật Loại sản phẩm:Hai Mảnh swimsuit kids:Kids Swimsuit UPF 50 Sunscreen:UV Sun Protection bathing suit child:swimsuit for children baby dinosaur swimwear:Baby Swimsuit With sleeves:Short Sleeved Baby Rash Guard Swimsuits for Boys:baby swimwear UV swimsuit boy:children swimming suit children's swimwear:children's swimsuit baby bathing suit:children swimming suit swimsuit kids boy:boy's swimsuit swimsuit boy:children's bathing suit Giá sản phẩm trên Tiki đã bao gồm thuế theo luật hiện hành. Bên cạnh đó, tuỳ vào loại sản phẩm, hình thức và địa chỉ giao hàng mà có thể phát sinh thêm chi phí khác như phí vận chuyển, phụ phí hàng cồng kềnh, thuế nhập khẩu (đối với đơn hàng giao từ nước ngoài có giá trị trên 1 triệu đồng).....",
        "images_url": [
            "https://salt.tikicdn.com/ts/product/2f/42/0e/4fbe5c7c2eeaa0053813e45d0fea2ebc.jpg",
            "https://salt.tikicdn.com/ts/product/bf/02/1e/9da47e30a4441223259896570f644c24.jpg",
            "https://salt.tikicdn.com/ts/product/ab/4b/49/d04eadf60237cf0b50d85074a1bd03b8.jpg",
            "https://salt.tikicdn.com/ts/product/3e/fc/6c/0144c1885ed2b7bec0c2421315ef9252.jpg",
            "https://salt.tikicdn.com/ts/product/12/d2/39/a7e295a2c32a3f6b8b24ce2512a0c9ce.jpg",
            "https://salt.tikicdn.com/ts/product/97/c5/4a/61a1579d02a1ba0380ee5698b1ddd0a1.jpg"
        ]
    },
    {
        "id": 124515574,
        "name": "2019 công chúa ba lô với my little pony phim hoạt hình túi thiết kế trường học cho bé nhỏ của tôi pony túi quà tặng đối với kid ngựa nhỏ của tôi trở lại",
        "url_key": "2019-cong-chua-ba-lo-voi-my-little-pony-phim-hoat-hinh-tui-thiet-ke-truong-hoc-cho-be-nho-cua-toi-pony-tui-qua-tang-doi-voi-kid-ngua-nho-cua-toi-tro-lai-p124515574",
        "price": 748650,
        "description": "Loại sản phẩm:Ba lô Chất liệu chính:NYLON trang trí:Flowers trang trí:NONE trang trí:Chuỗi giới tính:Cô gái Loại mô hình:Việc vá lại ba lô Loại:Softback Loại đóng cửa:zipper Vật liệu lót:Polyester công suất:20-35 lít Che mưa:Không thực hiện hệ thống:Đệm không khí Belt Số mô hình:my little pony new ngoại thất:Túi rắn phong cách:Thời Trang Handle/Strap Type:Soft Handle nội thất:Điện thoại di động bỏ túi nội thất:Khe cắm Pocket nội thất kỷ thuật học:Dập nổi SIZE:29*18*42CM Backpack Usage:Daily Backpack Capacity:20-35 Litre Main Material:Polyester Giá sản phẩm trên Tiki đã bao gồm thuế theo luật hiện hành. Bên cạnh đó, tuỳ vào loại sản phẩm, hình thức và địa chỉ giao hàng mà có thể phát sinh thêm chi phí khác như phí vận chuyển, phụ phí hàng cồng kềnh, thuế nhập khẩu (đối với đơn hàng giao từ nước ngoài có giá trị trên 1 triệu đồng).....",
        "images_url": [
            "https://salt.tikicdn.com/ts/product/96/d8/c5/77e6e27737eb828b0f90b0fe784dff79.jpg",
            "https://salt.tikicdn.com/ts/product/46/ce/e9/e534179a3441e52a558df255e51c2bbc.jpg",
            "https://salt.tikicdn.com/ts/product/8f/67/f0/a0cd3ebb4f8b3ec222599804c55021bc.jpg",
            "https://salt.tikicdn.com/ts/product/d6/d4/8c/3f32ec88a717bccc7d422a420a956dc1.jpg",
            "https://salt.tikicdn.com/ts/product/8f/cf/e7/03dfaffe84ffcecb61545e6a20638ffd.jpg",
            "https://salt.tikicdn.com/ts/product/a3/fa/f9/8cdd3ec7c2791f9d1ecf2307da9b9df2.jpg"
        ]
    },
    {
        "id": 204720318,
        "name": "Rainbow Birthday Party   Photo Prop 1 Year",
        "url_key": "rainbow-birthday-party-photo-prop-1-year-p204720318",
        "price": 167000,
        "description": "Description: Birthday Caps: supplies, Compact shape, beautiful and exquisite in pattern. Portable: expanded, easy to carry and Material: Made non woven fabric and felt, comfortable and durable. included: headband Birthday Headband:Perfect accessories for Birthday celebrations or . Specification: Material: Felt cloth Size Chart: The expanded length is about 26.5cm/10.43inch and the width is about 7cm/76inch, The diameter is about 8cm/07inch Includes: 1 Birthday Caps Note: Please allow slightly errors due to manual measurement and monitors. Giá sản phẩm trên Tiki đã bao gồm thuế theo luật hiện hành. Bên cạnh đó, tuỳ vào loại sản phẩm, hình thức và địa chỉ giao hàng mà có thể phát sinh thêm chi phí khác như phí vận chuyển, phụ phí hàng cồng kềnh, thuế nhập khẩu (đối với đơn hàng giao từ nước ngoài có giá trị trên 1 triệu đồng).....",
        "images_url": [
            "https://salt.tikicdn.com/ts/product/c1/a4/e1/9dfff122641cf7af9880172b0de73309.jpg",
            "https://salt.tikicdn.com/ts/product/c7/81/4f/4a5f2fb7de10cdd1961b06f60a9b85e2.jpg",
            "https://salt.tikicdn.com/ts/product/2f/99/7b/dc4b7ef9c8e39e82af0bc2ed7a131832.jpg",
            "https://salt.tikicdn.com/ts/product/ce/3b/4d/ff9590467c6530bf2bd639d23e6c17e9.jpg",
            "https://salt.tikicdn.com/ts/product/b8/aa/e0/d37372975c881e9866e7c5c39298fd17.jpg",
            "https://salt.tikicdn.com/ts/product/00/c2/ff/ee5b9432251c1dfc7f5311b389196972.jpg",
            "https://salt.tikicdn.com/ts/product/9c/c5/a7/c326743a65b9703bb6d2612c4dd1bfd7.jpg",
            "https://salt.tikicdn.com/ts/product/3b/41/99/e1beebe728308cc8a816cabbb797e087.jpg",
            "https://salt.tikicdn.com/ts/product/eb/7d/e1/0612dd4ba3696740eb404267fd702651.jpg"
        ]
    },
    {
        "id": 59093520,
        "name": "Toddler Kids Girl Boy Vintage Flower Round Anti-UV Sunglasses, Colorful Cute Eyewear Suit for Party Photography Outdoor Beach",
        "url_key": "toddler-kids-girl-boy-vintage-flower-round-anti-uv-sunglasses-colorful-cute-eyewear-suit-for-party-photography-outdoor-beach-p59093520",
        "price": 89000,
        "description": "Size Chart: Size:Approx.16x13cm/6.3x5.1inch Package Includes: 1 Piece sunglasses Giá sản phẩm trên Tiki đã bao gồm thuế theo luật hiện hành. Bên cạnh đó, tuỳ vào loại sản phẩm, hình thức và địa chỉ giao hàng mà có thể phát sinh thêm chi phí khác như phí vận chuyển, phụ phí hàng cồng kềnh, thuế nhập khẩu (đối với đơn hàng giao từ nước ngoài có giá trị trên 1 triệu đồng).....",
        "images_url": [
            "https://salt.tikicdn.com/ts/product/f7/f2/14/1df071ef0e13bd4017d7ea00112aefa4.jpg",
            "https://salt.tikicdn.com/ts/product/a6/52/a4/6fed54eb6dfb9273b659195c2c0ae2f2.jpg",
            "https://salt.tikicdn.com/ts/product/e8/0d/85/980872c524734c559bba24cf72ced09d.jpg",
            "https://salt.tikicdn.com/ts/product/2a/5b/d9/93c9672c9bb49d6280e07081ca07a474.jpg",
            "https://salt.tikicdn.com/ts/product/5b/f3/71/e2632f18e48d25c752073e634e9a001c.jpg",
            "https://salt.tikicdn.com/ts/product/8b/e7/27/3d79b534015a3e86e87034049d733186.jpg",
            "https://salt.tikicdn.com/ts/product/48/ea/9c/9c13288d57d86924c257d17d08848ec6.jpg",
            "https://salt.tikicdn.com/ts/product/8a/f8/a1/7992116fc9fd211f2bf7196b2d9ec380.jpg",
            "https://salt.tikicdn.com/ts/product/b4/2f/de/78fb62475efa615d6aa0b6edeb3abfbe.jpg",
            "https://salt.tikicdn.com/ts/product/30/c5/a3/48473ccfed623f1dd4b26ac2e8bbd764.jpg",
            "https://salt.tikicdn.com/ts/product/52/5c/d1/e2601220442c5a331673da3c704b8ba1.jpg",
            "https://salt.tikicdn.com/ts/product/57/58/f5/27dea2e820419c3eae55f682bb119680.jpg"
        ]
    },
    {
        "id": 124623941,
        "name": "2021 Trẻ Em 1 Đồ Bơi 2 Mảnh Bé Trai Bé Gái Đồ Bơi Cho Bé 2-10 Tuổi Hoạt Hình Cho Bé ong Đầm Nón Vàng Hồng",
        "url_key": "2021-tre-em-1-do-boi-2-manh-be-trai-be-gai-do-boi-cho-be-2-10-tuoi-hoat-hinh-cho-be-ong-dam-non-vang-hong-p124623941",
        "price": 837522,
        "description": "nguồn gốc:CN (Nguồn Gốc) Chất liệu:NYLON giới tính:Cô gái Loại mô hình:Động vật Loại sản phẩm:Một miếng Loại thể thao:Swim Fit:Phù hợp với đúng kích thước, mất bình thường của bạn kích thước Số mô hình:bjn304 Color:Yellow Pattern:Bee Giá sản phẩm trên Tiki đã bao gồm thuế theo luật hiện hành. Bên cạnh đó, tuỳ vào loại sản phẩm, hình thức và địa chỉ giao hàng mà có thể phát sinh thêm chi phí khác như phí vận chuyển, phụ phí hàng cồng kềnh, thuế nhập khẩu (đối với đơn hàng giao từ nước ngoài có giá trị trên 1 triệu đồng).....",
        "images_url": [
            "https://salt.tikicdn.com/ts/product/11/8c/00/4803878cb9eb411b935884e6611aa547.jpg",
            "https://salt.tikicdn.com/ts/product/72/38/ef/466d9c1e1385661337f81a8c66de014b.jpg",
            "https://salt.tikicdn.com/ts/product/df/20/79/118856897dc4cef4f3d9006cb1ad2261.jpg",
            "https://salt.tikicdn.com/ts/product/60/fb/b5/eb0bb1a0e594944a645073f8e5ad9c51.jpg",
            "https://salt.tikicdn.com/ts/product/1f/84/81/1d3cbe2a22ca04a8a28be7f74df0f8e1.jpg",
            "https://salt.tikicdn.com/ts/product/43/a2/4c/2ec5a79966371df4dc2ea86e5f466b98.jpg"
        ]
    },
    {
        "id": 124496341,
        "name": "Đội Trưởng Đầu Lâu Cướp Biển Trang Phục Bé Trai Bé Gái Halloween Buccaneer Cosplay Bộ Trang Phục Mát Nón Quần Áo Cho Trẻ Sơ Sinh Cho Bé Con",
        "url_key": "doi-truong-dau-lau-cuop-bien-trang-phuc-be-trai-be-gai-halloween-buccaneer-cosplay-bo-trang-phuc-mat-non-quan-ao-cho-tre-so-sinh-cho-be-con-p124496341",
        "price": 702282,
        "description": "nguồn gốc:CN (Nguồn Gốc) thành phần:Lên trên thành phần:Quần thành phần:Váy Loại nguồn:HOLIDAY giới tính:Con trai Loại sản phẩm:Bộ nhân vật:Other Số mô hình:CTZ-SYXG-002A Chất liệu:Polyester Color:Blue Size:S,M,L Model:CTZ-XG-013A Giá sản phẩm trên Tiki đã bao gồm thuế theo luật hiện hành. Bên cạnh đó, tuỳ vào loại sản phẩm, hình thức và địa chỉ giao hàng mà có thể phát sinh thêm chi phí khác như phí vận chuyển, phụ phí hàng cồng kềnh, thuế nhập khẩu (đối với đơn hàng giao từ nước ngoài có giá trị trên 1 triệu đồng).....",
        "images_url": [
            "https://salt.tikicdn.com/ts/product/14/c0/df/2e1f55f9ad5f91bba714bd0f9d14b1b0.jpg",
            "https://salt.tikicdn.com/ts/product/50/0e/d8/4167b0cfcffa3a97d1b205f439f70125.jpg",
            "https://salt.tikicdn.com/ts/product/5c/e3/85/ca1d401c22645d18c453918b2da8c530.jpg",
            "https://salt.tikicdn.com/ts/product/3c/05/29/944a5943e4ba92b411bdb7502829c43c.jpg",
            "https://salt.tikicdn.com/ts/product/68/f2/39/2cd2d4dbf72331bbb2770cc9c5344c01.jpg",
            "https://salt.tikicdn.com/ts/product/ab/3a/4a/56c00c19d7bf0834b37fd6bbea3b38b1.jpg"
        ]
    },
    {
        "id": 200697310,
        "name": "Piggy Bank Electronic ATM Password   Saving Box Toy Gift",
        "url_key": "piggy-bank-electronic-atm-password-saving-box-toy-gift-p200697310",
        "price": 641000,
        "description": "Description: Kids toy ATM piggy bank designed with interesting face recognition function. Easy to set 4-digit password lock which can be changed at any time. Made of high quality ABS material, stylish and a beautiful, great eductional toy to help your kids start learning to save. Imitate the real ATM using situation, with sound and music when scrolling the paper money. Battery powered by 3 AA batteries (not included). Great gift for kids on their birthdays. Size Chart: 13.5x13.5x20.5cm/5.31x5.31x8.07inch Package Includes: 1 Piece Mini Bank Toy Note: Colors might be different due to different monitor display. Manual measurement may cause slightly difference in size. Giá sản phẩm trên Tiki đã bao gồm thuế theo luật hiện hành. Bên cạnh đó, tuỳ vào loại sản phẩm, hình thức và địa chỉ giao hàng mà có thể phát sinh thêm chi phí khác như phí vận chuyển, phụ phí hàng cồng kềnh, thuế nhập khẩu (đối với đơn hàng giao từ nước ngoài có giá trị trên 1 triệu đồng).....",
        "images_url": [
            "https://salt.tikicdn.com/ts/product/e0/90/97/5fecc5a3c9e72cc1e815826c56c1912b.jpg",
            "https://salt.tikicdn.com/ts/product/c7/c4/bf/82f02acad54c7b086297e12e271d2471.jpg",
            "https://salt.tikicdn.com/ts/product/8c/e9/87/03214704cd0a1739f0e1c42716af6da4.jpg",
            "https://salt.tikicdn.com/ts/product/8d/cd/65/37ba70c1ea1c3c50a11776655ab79df1.jpg"
        ]
    },
    {
        "id": 101062352,
        "name": "Halloween Costumes Wizard Cloak with Hat for Kids Children Boys Girls",
        "url_key": "halloween-costumes-wizard-cloak-with-hat-for-kids-children-boys-girls-p101062352",
        "price": 97000,
        "description": "Description : Package Includes : 1 Piece Hat 1 Piece Cape Giá sản phẩm trên Tiki đã bao gồm thuế theo luật hiện hành. Bên cạnh đó, tuỳ vào loại sản phẩm, hình thức và địa chỉ giao hàng mà có thể phát sinh thêm chi phí khác như phí vận chuyển, phụ phí hàng cồng kềnh, thuế nhập khẩu (đối với đơn hàng giao từ nước ngoài có giá trị trên 1 triệu đồng).....",
        "images_url": [
            "https://salt.tikicdn.com/ts/product/d8/98/be/546f6050eafcabf6e0bffbb51a601e49.jpg",
            "https://salt.tikicdn.com/ts/product/df/ae/b1/f4f784db1c70d12ad68d87d28cb94da3.jpg",
            "https://salt.tikicdn.com/ts/product/38/10/36/4132f1b4196c154d7e872f7ef0226c0c.jpg",
            "https://salt.tikicdn.com/ts/product/f3/ad/2b/51212d4e788b95e0723ebf4314002de6.jpg",
            "https://salt.tikicdn.com/ts/product/2f/33/d1/69bb24983e928b79d08ade037cf529ac.jpg",
            "https://salt.tikicdn.com/ts/product/d3/24/23/c31da00a3a50bbf95a627ef51d778e55.jpg",
            "https://salt.tikicdn.com/ts/product/45/3e/6b/8de4eb9db74c38e520c7978009f5ba04.jpg",
            "https://salt.tikicdn.com/ts/product/a4/80/ed/3b262dd9c148790ef5f803b53f0e531c.jpg",
            "https://salt.tikicdn.com/ts/product/03/34/a7/25ca277814d544a1708f107573613960.jpg",
            "https://salt.tikicdn.com/ts/product/ec/f8/5b/b6d4b3cc93f2c0ff578704e3c6ce3d3d.jpg",
            "https://salt.tikicdn.com/ts/product/dc/fe/58/66f8a0f405f3dba68dbc2db201a08046.jpg",
            "https://salt.tikicdn.com/ts/product/b1/8c/3e/6e024d5a91e027a25ece55d60b433952.jpg"
        ]
    },
    {
        "id": 124346934,
        "name": "Trẻ Sơ Sinh Bộ Quần Áo Cho Bé Nữ 2021 Thu Mùa Xuân Quần Áo Cho Bé Sơ Sinh Bé Trai Quần Áo Hoodie + Quần 2 Bộ Trang Phục trẻ Em Trang Phục",
        "url_key": "tre-so-sinh-bo-quan-ao-cho-be-nu-2021-thu-mua-xuan-quan-ao-cho-be-so-sinh-be-trai-quan-ao-hoodie-quan-2-bo-trang-phuc-tre-em-trang-phuc-p124346934",
        "price": 675717,
        "description": "Chất liệu:COTTON Chất liệu:Polyester Tuổi Phạm vi:0-6M Tuổi Phạm vi:7-12M Tuổi Phạm vi:13-24M nguồn gốc:CN (Nguồn Gốc) mùa:Spring & Autumn giới tính:Bé trai phong cách:Thời Trang cổ áo:Đội mũ trùm đầu Loại sản phẩm:Bộ Loại đóng cửa:Áo Thun Chui Đầu Sleeve Length (cm):Đầy đủ Kiểu tay áo:Sleeve bùng phát Fit:Phù hợp với đúng kích thước, mất bình thường của bạn kích thước Outerwear Type:Áo Khoác Loại mô hình:In Tên bộ phận:baby Số mô hình:cartoon Giá sản phẩm trên Tiki đã bao gồm thuế theo luật hiện hành. Bên cạnh đó, tuỳ vào loại sản phẩm, hình thức và địa chỉ giao hàng mà có thể phát sinh thêm chi phí khác như phí vận chuyển, phụ phí hàng cồng kềnh, thuế nhập khẩu (đối với đơn hàng giao từ nước ngoài có giá trị trên 1 triệu đồng).....",
        "images_url": [
            "https://salt.tikicdn.com/ts/product/fb/e0/1c/5afecbfb178f92307e3bfd8417ca7ba6.jpg",
            "https://salt.tikicdn.com/ts/product/8f/4a/7a/e5a3677e9b7c6184151a2a705e17aade.jpg",
            "https://salt.tikicdn.com/ts/product/cf/16/11/6c646c42a2154c737f6038e873bcff8c.jpg",
            "https://salt.tikicdn.com/ts/product/9e/b4/80/c508f4ad9cd65fd6626b44b94b4e611e.jpg",
            "https://salt.tikicdn.com/ts/product/63/f7/13/6141cb6f4032aa94ad2f7be55bebe4c5.jpg",
            "https://salt.tikicdn.com/ts/product/14/2e/86/e69f3e0a3be36de0e1c5e1f991d14ebc.jpg"
        ]
    },
    {
        "id": 184906731,
        "name": "Bộ Đồ Ngủ Trẻ Em Onesie Hình Gấu Báo Cho Trẻ Em 2022 Chăn Hoạt Hình Động Vật Trang Phục Ngủ Cho Bé Bộ Đồ Ngủ Mùa Đông Cho Bé Trai Bé Gái",
        "url_key": "bo-do-ngu-tre-em-onesie-hinh-gau-bao-cho-tre-em-2022-chan-hoat-hinh-dong-vat-trang-phuc-ngu-cho-be-bo-do-ngu-mua-dong-cho-be-trai-be-gai-p184906731",
        "price": 333331,
        "description": "Kích thước là unisex, vì vậy bất kể bạn là nam hay nữ, bạn đều có thể mặc nó, chúng tôi cũng đề nghị bạn có thể sử dụng làm đồ ngủ cặp đôi, bạn có thể phối hợp nó, như đường may màu xanh và hồng, ma quỷ và dơi, Vân vân Có khóa kéo quanh hông, rất dễ dàng đi phòng tắm; Xin vui lòng cho tôi biết nếu bạn muốn nhiều hơn, chúng tôi sẽ cung cấp cho bạn một mức giá tốt với vận chuyển nhanh chóng!Cảm ơn! Kích thước trẻ em: 4t / 100: Vừa 88-105cm (Chiều cao) 6t / 110: Vừa 105-115cm (Chiều cao) 8t / 120: Vừa vặn 116-125cm (Chiều cao) 10t / 130: Vừa vặn 125-135cm (Chiều cao) 12t / 140: Phù hợp135-145cm (Chiều cao) So sánh kích thước chi tiết với của bạn, vui lòng cho phép chênh lệch 1-2CM do đo lường thủ công, cảm ơn Lưu ý: Do sự khác biệt giữa các màn hình khác nhau, hình ảnh có thể không phản ánh màu sắc thực tế của sản phẩm. Chúng tôi đảm bảo mẫu mã giống như trong hình, nhưng mỗi người cho kết quả khác nhau. Cảm ơn bạn! Mặt hàng Bao gồm (không bao gồm Dép) 1x đồ ngủ Giá sản phẩm trên Tiki đã bao gồm thuế theo luật hiện hành. Bên cạnh đó, tuỳ vào loại sản phẩm, hình thức và địa chỉ giao hàng mà có thể phát sinh thêm chi phí khác như phí vận chuyển, phụ phí hàng cồng kềnh, thuế nhập khẩu (đối với đơn hàng giao từ nước ngoài có giá trị trên 1 triệu đồng).....",
        "images_url": [
            "https://salt.tikicdn.com/media/catalog/product/f5/15/2228f38cf84d1b8451bb49e2c4537081.png"
        ]
    },
    {
        "id": 184903194,
        "name": "Bộ Đồ Ngủ Minion Bộ Đồ Ngủ Hóa Trang Động Vật Cho Bé Trai Bé Gái Kigurumi Bộ Đồ Liền Thân Cho Trẻ Tập Đi",
        "url_key": "bo-do-ngu-minion-bo-do-ngu-hoa-trang-dong-vat-cho-be-trai-be-gai-kigurumi-bo-do-lien-than-cho-tre-tap-di-p184903194",
        "price": 333331,
        "description": "Kích thước là unisex, vì vậy bất kể bạn là nam hay nữ, bạn đều có thể mặc nó, chúng tôi cũng đề nghị bạn có thể sử dụng làm đồ ngủ cặp đôi, bạn có thể phối hợp nó, như đường may màu xanh và hồng, ma quỷ và dơi, Vân vân Có khóa kéo quanh hông, rất dễ dàng đi phòng tắm; Xin vui lòng cho tôi biết nếu bạn muốn nhiều hơn, chúng tôi sẽ cung cấp cho bạn một mức giá tốt với vận chuyển nhanh chóng!Cảm ơn! Kích thước trẻ em: 4t / 100: Vừa 88-105cm (Chiều cao) 6t / 110: Vừa 105-115cm (Chiều cao) 8t / 120: Vừa vặn 116-125cm (Chiều cao) 10t / 130: Vừa vặn 125-135cm (Chiều cao) 12t / 140: Phù hợp135-145cm (Chiều cao) So sánh kích thước chi tiết với của bạn, vui lòng cho phép chênh lệch 1-2CM do đo lường thủ công, cảm ơn Lưu ý: Do sự khác biệt giữa các màn hình khác nhau, hình ảnh có thể không phản ánh màu sắc thực tế của sản phẩm. Chúng tôi đảm bảo mẫu mã giống như trong hình, nhưng mỗi người cho kết quả khác nhau. Cảm ơn bạn! Mặt hàng Bao gồm (không bao gồm Dép) 1x đồ ngủ Giá sản phẩm trên Tiki đã bao gồm thuế theo luật hiện hành. Bên cạnh đó, tuỳ vào loại sản phẩm, hình thức và địa chỉ giao hàng mà có thể phát sinh thêm chi phí khác như phí vận chuyển, phụ phí hàng cồng kềnh, thuế nhập khẩu (đối với đơn hàng giao từ nước ngoài có giá trị trên 1 triệu đồng).....",
        "images_url": [
            "https://salt.tikicdn.com/media/catalog/product/f5/15/2228f38cf84d1b8451bb49e2c4537081.png"
        ]
    },
    {
        "id": 124500190,
        "name": "Kỳ Lân Schoolbag Trẻ Em Mochila Đôi Vai Trường Túi Hoạt Hình Ba Lô Chống Thấm Nước Thời Trang Ba Lô Lớn Túi Sách",
        "url_key": "ky-lan-schoolbag-tre-em-mochila-doi-vai-truong-tui-hoat-hinh-ba-lo-chong-tham-nuoc-thoi-trang-ba-lo-lon-tui-sach-p124500190",
        "price": 512463,
        "description": "nguồn gốc:CN (Nguồn Gốc) Tuổi Phạm vi:7-12y Tuổi Phạm vi:4-6y Tuổi Phạm vi:25-36M Chất liệu chính:NYLON Loại sản phẩm:Ba Lô Trẻ Em Loại đóng cửa:zipper loại:Backpack Loại mô hình:In động vật Giá sản phẩm trên Tiki đã bao gồm thuế theo luật hiện hành. Bên cạnh đó, tuỳ vào loại sản phẩm, hình thức và địa chỉ giao hàng mà có thể phát sinh thêm chi phí khác như phí vận chuyển, phụ phí hàng cồng kềnh, thuế nhập khẩu (đối với đơn hàng giao từ nước ngoài có giá trị trên 1 triệu đồng).....",
        "images_url": [
            "https://salt.tikicdn.com/ts/product/fe/9d/72/a7f4bd0c6e8b1de13fad7afa527e8543.jpg",
            "https://salt.tikicdn.com/ts/product/ba/d3/83/1751d3e29b248c09fde0bd5daaf02fca.jpg",
            "https://salt.tikicdn.com/ts/product/ee/11/fa/8004d097f5e88b563c909a615b6c9cae.jpg",
            "https://salt.tikicdn.com/ts/product/78/3b/7e/08341597a60d41c095dc5af74ed9ea64.jpg",
            "https://salt.tikicdn.com/ts/product/5c/35/d1/837d8da3d9173a50443d3830df96c064.jpg",
            "https://salt.tikicdn.com/ts/product/84/e8/08/847335b1334dd69d9ffecce4087d942b.jpg"
        ]
    },
    {
        "id": 124640408,
        "name": "Đầm Trẻ Em Kính Mát Kính Chống Nắng Hoa Tròn Edge Bé Trẻ Em Uv400 Ngoài Trời Xe Thể Thao Kính Mắt Cho Bé Gái Bé Trai",
        "url_key": "dam-tre-em-kinh-mat-kinh-chong-nang-hoa-tron-edge-be-tre-em-uv400-ngoai-troi-xe-the-thao-kinh-mat-cho-be-gai-be-trai-p124640408",
        "price": 496524,
        "description": "nguồn gốc:CN (Nguồn Gốc) Các tính năng đặc biệt:Anti-glare Keyword1:Sunglasses Streetwear Keyword2:Car Driving Glasses Keyword3:UV 400 Eyewear Keyword4:Kids Polarized Sunglasses Giá sản phẩm trên Tiki đã bao gồm thuế theo luật hiện hành. Bên cạnh đó, tuỳ vào loại sản phẩm, hình thức và địa chỉ giao hàng mà có thể phát sinh thêm chi phí khác như phí vận chuyển, phụ phí hàng cồng kềnh, thuế nhập khẩu (đối với đơn hàng giao từ nước ngoài có giá trị trên 1 triệu đồng).....",
        "images_url": [
            "https://salt.tikicdn.com/ts/product/10/46/37/c155573247e8d132d2038bc6b7fbfd56.jpeg",
            "https://salt.tikicdn.com/ts/product/08/bd/ac/438cbbe84d99e5098a1c016eb12cb0f5.jpeg",
            "https://salt.tikicdn.com/ts/product/2d/69/92/a2eb67a75c61342567be3adc1244334f.jpeg",
            "https://salt.tikicdn.com/ts/product/b6/44/fc/a285444fd3e1d9fc3bdfafdceeb3a7c5.jpeg",
            "https://salt.tikicdn.com/ts/product/2c/2d/02/ede52d86d0c4381c54474506104b084f.jpeg",
            "https://salt.tikicdn.com/ts/product/41/02/52/18424c38a601b27a270bd9cab8e6fd1a.jpeg"
        ]
    },
    {
        "id": 120562370,
        "name": "Youpin Topbright Solid Wooden Animal Cascading Building Block Toy Set Children's Early Education Balanced Sense",
        "url_key": "youpin-topbright-solid-wooden-animal-cascading-building-block-toy-set-children-s-early-education-balanced-sense-p120562370",
        "price": 647800,
        "description": "Please note it,this item comes from Ecochain Cooperation, specialized in best products with the best quality, so there is no logo on it, thanks. Much More Hottest Ecochain Products on Youpin. Features: *Solid wood production, eco-friendly and durable, non-toxic and odorless *Playing method of taking turns to draw the bottom block,exercises children's spatial thinking ability and observation ability *The blocks can also be stacked into different shapes toimprove baby's creative thinking *Suitable for family to play games together,promote parent-child communication *Exquisite workmanship, smooth edges without burrs, will not hurt child's hands *Fresh colors with animal element, attract baby's eyeball *Suitable age:3 years old+ Specifiction: Product name: Animal building Item weight: 1000g/35.27oz Package weight: 1500/52.91 Package size: 11.6*8.2*25.4cm/4.56*3.22*10in Material: wood Suitable age: More than 3 years old Package list: 1* TopbrightBuilding Block Toy Giá sản phẩm trên Tiki đã bao gồm thuế theo luật hiện hành. Bên cạnh đó, tuỳ vào loại sản phẩm, hình thức và địa chỉ giao hàng mà có thể phát sinh thêm chi phí khác như phí vận chuyển, phụ phí hàng cồng kềnh, thuế nhập khẩu (đối với đơn hàng giao từ nước ngoài có giá trị trên 1 triệu đồng).....",
        "images_url": [
            "https://salt.tikicdn.com/ts/product/51/cf/55/521f672f46f49e50efc3aa19a4204ab8.jpg",
            "https://salt.tikicdn.com/ts/product/b7/17/61/b963f00296b444b05648862efae5b186.jpg",
            "https://salt.tikicdn.com/ts/product/e8/9c/ce/14e9fe53a4b73f41697b42c0c2fd9ca9.jpg",
            "https://salt.tikicdn.com/ts/product/fd/a3/8b/365add21045cca137730b2f781904833.jpg",
            "https://salt.tikicdn.com/ts/product/0c/88/e2/653cd8c5a729c9c602ae8a4e931b7184.jpg",
            "https://salt.tikicdn.com/ts/product/b0/67/cc/fd834222cf01d395018471c3b4a96ba2.jpg"
        ]
    },
    {
        "id": 124581578,
        "name": "Cầu Vồng Đuôi Cá Nàng Tiên Cá Đuôi Trang Phục Trẻ Em Người Cá Cosplay Bé Gái Lạ Mắt Đầm Halloween",
        "url_key": "cau-vong-duoi-ca-nang-tien-ca-duoi-trang-phuc-tre-em-nguoi-ca-cosplay-be-gai-la-mat-dam-halloween-p124581578",
        "price": 561246,
        "description": "nguồn gốc:CN (Nguồn Gốc) Loại mô hình:Động vật Loại sản phẩm:Bikinis Set Giá sản phẩm trên Tiki đã bao gồm thuế theo luật hiện hành. Bên cạnh đó, tuỳ vào loại sản phẩm, hình thức và địa chỉ giao hàng mà có thể phát sinh thêm chi phí khác như phí vận chuyển, phụ phí hàng cồng kềnh, thuế nhập khẩu (đối với đơn hàng giao từ nước ngoài có giá trị trên 1 triệu đồng).....",
        "images_url": [
            "https://salt.tikicdn.com/ts/product/0c/82/42/839fcf9fbd85b97c47a73412d7097705.jpg",
            "https://salt.tikicdn.com/ts/product/19/7d/d2/5067082759c997e75f73917d7f7f73d8.jpg",
            "https://salt.tikicdn.com/ts/product/41/1b/b0/6890091a24ea7174b3c3d3ebaa059188.jpg",
            "https://salt.tikicdn.com/ts/product/82/9e/03/75666e2da69b7b7e1483bebaf2ae6dfa.jpg",
            "https://salt.tikicdn.com/ts/product/45/02/0f/c6a2f79abc1963e865fd36ffc152b908.jpg",
            "https://salt.tikicdn.com/ts/product/7d/7c/58/167bf371313270d65daa843cf4b213bc.jpg"
        ]
    },
    {
        "id": 124499096,
        "name": "Cocomelon Ba Lô Cho Bé Sinh Đựng Trẻ Em Mẫu Giáo Trường Túi Trẻ Em Anime Ba Lô Bé Trai Bé Gái Hoạt Hình Có Túi Quà Tặng Dễ Thương",
        "url_key": "cocomelon-ba-lo-cho-be-sinh-dung-tre-em-mau-giao-truong-tui-tre-em-anime-ba-lo-be-trai-be-gai-hoat-hinh-co-tui-qua-tang-de-thuong-p124499096",
        "price": 499905,
        "description": "Chất liệu chính:NYLON nguồn gốc:CN (Nguồn Gốc) kỷ thuật học:Dập nổi giới tính:Unisex ba lô Loại:Softback công suất:Dưới 20 lít nội thất:Nội thất khoang Handle/Strap Type:Soft Handle Loại sản phẩm:Ba lô trang trí:NONE trang trí:Cocomelon Printing Loại đóng cửa:zipper Che mưa:Không ngoại thất:NONE thực hiện hệ thống:Arcuate Dây đeo vai Số mô hình:12 inch Cocomelon Backpack Vật liệu lót:Polyester phong cách:Bình thường Loại mô hình:Hình Hoạt Hình kids kindergarten Bags:Cocomelon backpacks kids Kindergarten Backpack:New Cocomelon School Backpack Cocomelon backpack for girls:Cute Cocomelon School Bags backpack for boys:Children's Backpack Girls Boys School Bag:School Backpacks Giá sản phẩm trên Tiki đã bao gồm thuế theo luật hiện hành. Bên cạnh đó, tuỳ vào loại sản phẩm, hình thức và địa chỉ giao hàng mà có thể phát sinh thêm chi phí khác như phí vận chuyển, phụ phí hàng cồng kềnh, thuế nhập khẩu (đối với đơn hàng giao từ nước ngoài có giá trị trên 1 triệu đồng).....",
        "images_url": [
            "https://salt.tikicdn.com/ts/product/4c/05/4c/9c592ac1952fb3840fd3b567e8448ff3.jpg",
            "https://salt.tikicdn.com/ts/product/75/26/96/a431f6cb4206a3ffad98a51bebc256ce.jpg",
            "https://salt.tikicdn.com/ts/product/35/c1/c2/c8fbd5f63daf8c314c433b609d10c132.jpg",
            "https://salt.tikicdn.com/ts/product/05/dd/4d/036c5e198110d7d89ba687b6b2cbda94.jpg",
            "https://salt.tikicdn.com/ts/product/2a/97/7d/5b24f6a82a1d39b9b1c50b8b97c19c24.jpg",
            "https://salt.tikicdn.com/ts/product/cc/2c/93/cd4861643b8d3915a5b9bba2cd6534d8.jpg"
        ]
    },
    {
        "id": 120562362,
        "name": "490 Pcs Xiaomi Desert Racing Car Building Blocks Set DIY Toys Smart Linkage System Independent Suspension DIY",
        "url_key": "490-pcs-xiaomi-desert-racing-car-building-blocks-set-diy-toys-smart-linkage-system-independent-suspension-diy-p120562362",
        "price": 999800,
        "description": "490 Pcs Xiaomi Desert Racing Car Building Blocks Set DIY Toys Smart Linkage System Independent Suspension DIY Educational Gifts for Kids Note: This product is xiaomi ecological chain brand product, there is no any xiaomi marks on the products, please note it. Features: - Over 490pcs block bricks designed with a combination of block and racing car offer much more fun for your kids. - Sophisticated mechanical transmission and pure mechanical control system enable bring up your kids'manual abilities. - Cylinder piston linkage stimulates the inner structure of real cars, powerful enough for car running fast. - The racing car enhances the wheels' stability and smooth speed thanks to the stimulation of real cars' suspension system. - Adopts all-new rotating equipment, big tail design and the cool stick as gift, which makes your car awesome and outstanding. - Lightweight body with mechanical skeleton frame and high shock absorption, effectively increases car's security. Specification: Brand: Xiaomi Type: Building Block Materials: ABS,PC Theme: Vehicle Suitable Age: Kids Gender: Unisex Product weight: 525g/18.52oz Package weight: 625g/21.16oz Product size: Approx. 30.70 x 20.40 x 16.20 cm / 12.09 x 8.03 x 6.38 in Package size: Approx. 32.20 x 24.50 x 6.00 cm / 12.68 x 9.65 x 2.36 in Package List: 6 x Bag of Building Blocks 4 x Rubber Tire 1 x Chinese Instruction 1 x Sticker 1 x Chinese Building Manual Giá sản phẩm trên Tiki đã bao gồm thuế theo luật hiện hành. Bên cạnh đó, tuỳ vào loại sản phẩm, hình thức và địa chỉ giao hàng mà có thể phát sinh thêm chi phí khác như phí vận chuyển, phụ phí hàng cồng kềnh, thuế nhập khẩu (đối với đơn hàng giao từ nước ngoài có giá trị trên 1 triệu đồng).....",
        "images_url": [
            "https://salt.tikicdn.com/ts/product/d6/30/87/13c8b238a460f438e8639673964a23e9.jpg",
            "https://salt.tikicdn.com/ts/product/bd/0a/67/7f0bb169587b904d9223884f03c382e9.jpg",
            "https://salt.tikicdn.com/ts/product/d6/30/87/22e22568819096e8f7b3a4e36a9e4d94.jpg",
            "https://salt.tikicdn.com/ts/product/31/c7/85/e91bbffc462fc684f1363e2400c51b09.jpg",
            "https://salt.tikicdn.com/ts/product/f7/63/b5/6beeb7eb76a5702e515d1b71d33aa5a8.jpg",
            "https://salt.tikicdn.com/ts/product/b5/07/43/4e24c90b2cd6d05e602c1b2508b2c77d.jpg",
            "https://salt.tikicdn.com/ts/product/a1/8b/7d/1131dfcaae7666cdde00c3041b9701cd.jpg",
            "https://salt.tikicdn.com/ts/product/52/3c/6f/3dea008f10d24926d1aadb6c5b204eac.jpg"
        ]
    },
    {
        "id": 204706447,
        "name": "1pc  Roll Over Monkey Toy with Light Interesting Educational Toy",
        "url_key": "1pc-roll-over-monkey-toy-with-light-interesting-educational-toy-p204706447",
        "price": 424000,
        "description": "Description: Sound control, environmentally friendly material, cute shape, non-toxic, safe for kids. Press the switch, it will roll up and down and make the baby laugh happily. Clap your hands, make a sound, and the little monkey will roll over with the lights. Rotate the arm 360 degrees freely to achieve a . increase the fun of playing and let children feel an entertaining atmosphere. Best gift, baby\\'s best friend. Specification: Material: Plastic Fit for 6 Months and up. Power Supply: 3 AAA battery (not included) Size Chart: Size: 13.5x9x9cm/5.31x3.54x3.54inch Package Includes: 1 Piece Voice Control Roll Over Monkey Toy. : Color might be slightly different due to the color calibration of each individual monitor. Please allow slightly measuring deviation due to manual measurement. Giá sản phẩm trên Tiki đã bao gồm thuế theo luật hiện hành. Bên cạnh đó, tuỳ vào loại sản phẩm, hình thức và địa chỉ giao hàng mà có thể phát sinh thêm chi phí khác như phí vận chuyển, phụ phí hàng cồng kềnh, thuế nhập khẩu (đối với đơn hàng giao từ nước ngoài có giá trị trên 1 triệu đồng).....",
        "images_url": [
            "https://salt.tikicdn.com/ts/product/7e/bf/51/108c47d6e0d36dd84cf51bdfc4197cc0.jpg",
            "https://salt.tikicdn.com/ts/product/d5/03/be/161b6e897254cd5c9ec853855ff30d24.jpg",
            "https://salt.tikicdn.com/ts/product/0a/01/15/de7d1f848a1c7d3095395a268c195730.jpg",
            "https://salt.tikicdn.com/ts/product/a2/2b/f1/0fb3aed5c02e5b510125428519105007.jpg",
            "https://salt.tikicdn.com/ts/product/ae/56/43/be1abf3cbfded9d4a8d69b8bbc111178.jpg",
            "https://salt.tikicdn.com/ts/product/24/0d/be/ab09392be3e3eb200d25e811f76ee417.jpg",
            "https://salt.tikicdn.com/ts/product/5b/df/34/8d9a76a870aa605f4684c4d872366cd9.jpg",
            "https://salt.tikicdn.com/ts/product/59/e5/d2/3f6ea88d68ae7c176bd349c666c8dd98.jpg",
            "https://salt.tikicdn.com/ts/product/af/b2/b6/165ea8bb9943213f9ba98a62740b6eb8.jpg"
        ]
    },
    {
        "id": 184940994,
        "name": "Bộ Đồ Ngủ Trẻ Em Hình Động Vật Bằng Vải Flanen Đồ Ngủ Trẻ Em Hoạt Hình Sói Động Vật Có Mũ Mùa Đông Cho Bé Trai Bé Gái Đồ Ngủ Một Mảnh",
        "url_key": "bo-do-ngu-tre-em-hinh-dong-vat-bang-vai-flanen-do-ngu-tre-em-hoat-hinh-soi-dong-vat-co-mu-mua-dong-cho-be-trai-be-gai-do-ngu-mot-manh-p184940994",
        "price": 350000,
        "description": "Kích thước là unisex, vì vậy bất kể bạn là nam hay nữ, bạn đều có thể mặc nó, chúng tôi cũng đề nghị bạn có thể sử dụng làm đồ ngủ cặp đôi, bạn có thể phối hợp nó, như đường may màu xanh và hồng, ma quỷ và dơi, Vân vân Có khóa kéo quanh hông, rất dễ dàng đi phòng tắm; Xin vui lòng cho tôi biết nếu bạn muốn nhiều hơn, chúng tôi sẽ cung cấp cho bạn một mức giá tốt với vận chuyển nhanh chóng!Cảm ơn! Kích thước trẻ em: 4t / 100: Vừa 88-105cm (Chiều cao) 6t / 110: Vừa 105-115cm (Chiều cao) 8t / 120: Vừa vặn 116-125cm (Chiều cao) 10t / 130: Vừa vặn 125-135cm (Chiều cao) 12t / 140: Phù hợp135-145cm (Chiều cao) So sánh kích thước chi tiết với của bạn, vui lòng cho phép chênh lệch 1-2CM do đo lường thủ công, cảm ơn Lưu ý: Do sự khác biệt giữa các màn hình khác nhau, hình ảnh có thể không phản ánh màu sắc thực tế của sản phẩm. Chúng tôi đảm bảo mẫu mã giống như trong hình, nhưng mỗi người cho kết quả khác nhau. Cảm ơn bạn! Mặt hàng Bao gồm (không bao gồm Dép) 1x đồ ngủ Giá sản phẩm trên Tiki đã bao gồm thuế theo luật hiện hành. Bên cạnh đó, tuỳ vào loại sản phẩm, hình thức và địa chỉ giao hàng mà có thể phát sinh thêm chi phí khác như phí vận chuyển, phụ phí hàng cồng kềnh, thuế nhập khẩu (đối với đơn hàng giao từ nước ngoài có giá trị trên 1 triệu đồng).....",
        "images_url": [
            "https://salt.tikicdn.com/media/catalog/product/f5/15/2228f38cf84d1b8451bb49e2c4537081.png"
        ]
    },
    {
        "id": 96689760,
        "name": "Kid Anti Noise Earmuffs Folding Sleep Protectors Muff 0-5 years Yellow",
        "url_key": "kid-anti-noise-earmuffs-folding-sleep-protectors-muff-0-5-years-yellow-p96689760",
        "price": 262000,
        "description": "Package Includes: 1pc Earmuff Note: The color may be different for different display, pls understand Pls allow 0-3cm error due to hand tste, thank you Giá sản phẩm trên Tiki đã bao gồm thuế theo luật hiện hành. Bên cạnh đó, tuỳ vào loại sản phẩm, hình thức và địa chỉ giao hàng mà có thể phát sinh thêm chi phí khác như phí vận chuyển, phụ phí hàng cồng kềnh, thuế nhập khẩu (đối với đơn hàng giao từ nước ngoài có giá trị trên 1 triệu đồng).....",
        "images_url": [
            "https://salt.tikicdn.com/ts/product/f8/bb/18/03c31e0e930f97cd66a2c21b589c2fd9.jpg",
            "https://salt.tikicdn.com/ts/product/88/20/b9/a69b80431c4a7dc4fa30b30e109fcb64.jpg",
            "https://salt.tikicdn.com/ts/product/18/4b/41/489c45d1782f798d326e3297b7fd6186.jpg",
            "https://salt.tikicdn.com/ts/product/f8/f0/36/1c8602bd5dcd4b10e14b88f805122865.jpg",
            "https://salt.tikicdn.com/ts/product/b2/d3/be/9cbcfccf53b19122a7e1a00b9f1d40ef.jpg",
            "https://salt.tikicdn.com/ts/product/0d/8c/1a/8463700c582623507f7fb7a77241a963.jpg",
            "https://salt.tikicdn.com/ts/product/e9/7b/f9/8ee99be54650be70e959ec1c26bc042c.jpg",
            "https://salt.tikicdn.com/ts/product/a3/4a/83/b978b873962ad885b215531fb18e32ce.jpg",
            "https://salt.tikicdn.com/ts/product/a3/4a/83/e3b34eefc66cfe0d81e9e1541ea15ea6.jpg",
            "https://salt.tikicdn.com/ts/product/71/7d/6e/a5147b9457e864030a3844c74a59f518.jpg",
            "https://salt.tikicdn.com/ts/product/a3/4a/83/b15c9845ff677d00f86671c44992ac73.jpg"
        ]
    },
    {
        "id": 120769852,
        "name": "Kids Step Stool Toddler Childs Stepping Pad Thickening Non-Slip Kitchen",
        "url_key": "kids-step-stool-toddler-childs-stepping-pad-thickening-non-slip-kitchen-p120769852",
        "price": 383000,
        "description": "Specification: Material: PP Polypropylene Package Includes: 1 Piece Step Stool Note: Color might be slightly different due to the color calibration of each individual monitor. Please allow slightly measuring deviation due to manual measurement. Giá sản phẩm trên Tiki đã bao gồm thuế theo luật hiện hành. Bên cạnh đó, tuỳ vào loại sản phẩm, hình thức và địa chỉ giao hàng mà có thể phát sinh thêm chi phí khác như phí vận chuyển, phụ phí hàng cồng kềnh, thuế nhập khẩu (đối với đơn hàng giao từ nước ngoài có giá trị trên 1 triệu đồng).....",
        "images_url": [
            "https://salt.tikicdn.com/ts/product/a3/9f/19/48f1a4f28e3384714ade74d6e46bce62.jpg",
            "https://salt.tikicdn.com/ts/product/67/bd/8f/b4a8f4d3bce4a7e6fa7808a58ddb40d4.jpg",
            "https://salt.tikicdn.com/ts/product/c7/f0/f3/e7e9b8b154430d4f428f9f8f90731e92.jpg",
            "https://salt.tikicdn.com/ts/product/96/9b/f8/6734c715bf52deff2b45fa701a167bc2.jpg",
            "https://salt.tikicdn.com/ts/product/56/a4/ae/1cdb82c60c556f4e95c7e85ac7ff5971.jpg",
            "https://salt.tikicdn.com/ts/product/f1/7e/17/94cdf02209eada33a138dfe7794f7a28.jpg",
            "https://salt.tikicdn.com/ts/product/02/b1/3d/a56d6bcbfaa096426f14095c659ec460.jpg",
            "https://salt.tikicdn.com/ts/product/30/e8/dc/a8afbac3ee1bdf980d6ba3ae71f0d849.jpg",
            "https://salt.tikicdn.com/ts/product/86/c3/51/7ecabaaa804a9af6cac74751fc728bae.jpg",
            "https://salt.tikicdn.com/ts/product/af/19/2b/f3e54b6ec05ef91ef6a1bd4a01da84a9.jpg",
            "https://salt.tikicdn.com/ts/product/39/1f/55/efbdd532e0250d39b3ba2b2743642cde.jpg",
            "https://salt.tikicdn.com/ts/product/2c/e8/83/82acdadc85642c8e45bf750d179ea582.jpg"
        ]
    },
    {
        "id": 204714300,
        "name": "Bird Plush Ornaments Stuffed Animal 20cm Cute for Bedroom White",
        "url_key": "bird-plush-ornaments-stuffed-animal-20cm-cute-for-bedroom-white-p204714300",
        "price": 261000,
        "description": "Description: Bird Plush: Our Bird toy, use this cute companion, soft bring to your children and girlfriend. Stuffed Doll: This stuffed animal Bird plush figure is high quality plush with filler, soft and . Fine Workmanship: With stitching and exquisite workmanship, not break or , flexibility, strong and durable. Great Gift: This animal Plush is a cute gift for families, friends, birthdays, housewarmings, and other parties. Applications: This Plush is suitable for living room, bedroom, office, car, etc. Specification: Product Size: Sitting Height 20cm/7.87inch Material: Plush Size Chart: Package Includes: 1 Bird Plush Giá sản phẩm trên Tiki đã bao gồm thuế theo luật hiện hành. Bên cạnh đó, tuỳ vào loại sản phẩm, hình thức và địa chỉ giao hàng mà có thể phát sinh thêm chi phí khác như phí vận chuyển, phụ phí hàng cồng kềnh, thuế nhập khẩu (đối với đơn hàng giao từ nước ngoài có giá trị trên 1 triệu đồng).....",
        "images_url": [
            "https://salt.tikicdn.com/ts/product/95/a0/b2/b097af3807deb5b8e6a9c073e9c710ed.jpg",
            "https://salt.tikicdn.com/ts/product/d3/82/19/5676c0d0b845aecc2abd50ddc8082caa.jpg",
            "https://salt.tikicdn.com/ts/product/5e/70/94/f5c2caa536008273bcec7cda08e62f05.jpg",
            "https://salt.tikicdn.com/ts/product/2d/83/c3/546de0c55925b1ea19a49d11ae088f0a.jpg",
            "https://salt.tikicdn.com/ts/product/40/50/d3/52f587310c6880248b1692dd5d99cd29.jpg",
            "https://salt.tikicdn.com/ts/product/9e/06/de/1846fd75551e843ea82cf2fceff2d6ca.jpg",
            "https://salt.tikicdn.com/ts/product/45/5f/84/9072b27db280536fcf92cc769c1cc716.jpg",
            "https://salt.tikicdn.com/ts/product/00/5f/60/081fd8cdca60d73fd5a1a6cb6422d20e.jpg",
            "https://salt.tikicdn.com/ts/product/5d/3a/ef/888eba12b4c5294874a529cea0f27e59.jpg"
        ]
    },
    {
        "id": 77725970,
        "name": "Rainbow Tower Ring Colored Kids Stacking Game Stacking Rings for Baby Boys",
        "url_key": "rainbow-tower-ring-colored-kids-stacking-game-stacking-rings-for-baby-boys-p77725970",
        "price": 150000,
        "description": "Package Includes: 1 Piece Wooden Ring Stacking Toy Giá sản phẩm trên Tiki đã bao gồm thuế theo luật hiện hành. Bên cạnh đó, tuỳ vào loại sản phẩm, hình thức và địa chỉ giao hàng mà có thể phát sinh thêm chi phí khác như phí vận chuyển, phụ phí hàng cồng kềnh, thuế nhập khẩu (đối với đơn hàng giao từ nước ngoài có giá trị trên 1 triệu đồng).....",
        "images_url": [
            "https://salt.tikicdn.com/ts/product/04/86/43/71868399c6a29d4cd4a11bfaf3101c6c.jpg",
            "https://salt.tikicdn.com/ts/product/0e/2b/b1/0331e0febb7d28a7b9b1f3d6b1a1e90c.jpg",
            "https://salt.tikicdn.com/ts/product/d7/5a/e6/9670fb648eebab468876f15f7c25b2dd.jpg",
            "https://salt.tikicdn.com/ts/product/7b/79/8f/b1802f4c4cd6a53b30c89bbc8fddf975.jpg",
            "https://salt.tikicdn.com/ts/product/ae/16/74/18147d64092384bf81440db38848cd83.jpg",
            "https://salt.tikicdn.com/ts/product/9a/11/d6/05d8b2271ea8eea3c5de58b2ef72f9d1.jpg",
            "https://salt.tikicdn.com/ts/product/c1/9b/e1/7e92d4fd5c0e39364bdef01ed010f9e5.jpg",
            "https://salt.tikicdn.com/ts/product/55/c2/f9/cce9c9735e4b6df085dd81c140d0ffbc.jpg",
            "https://salt.tikicdn.com/ts/product/d1/0f/0b/b202acc7c624224ead75c5f4a060d646.jpg",
            "https://salt.tikicdn.com/ts/product/66/41/1c/94482288ae0830757741ff0fe1593a31.jpg"
        ]
    },
    {
        "id": 184981740,
        "name": " Bộ Đồ Ngủ Liền Thân Dài Tay Mùa Đông Cho Bé Trai Bé Gái Bộ Áo Liền Quần Vải Flanen Hình Động Vật Hoạt Hình Kỳ Lân Tóc Xanh Bộ Đồ Ngủ Trẻ Em",
        "url_key": "bo-do-ngu-lien-than-dai-tay-mua-dong-cho-be-trai-be-gai-bo-ao-lien-quan-vai-flanen-hinh-dong-vat-hoat-hinh-ky-lan-toc-xanh-bo-do-ngu-tre-em-p184981740",
        "price": 350000,
        "description": "Kích thước là unisex, vì vậy bất kể bạn là nam hay nữ, bạn đều có thể mặc nó, chúng tôi cũng đề nghị bạn có thể sử dụng làm đồ ngủ cặp đôi, bạn có thể phối hợp nó, như đường may màu xanh và hồng, ma quỷ và dơi, Vân vân Có khóa kéo quanh hông, rất dễ dàng đi phòng tắm; Xin vui lòng cho tôi biết nếu bạn muốn nhiều hơn, chúng tôi sẽ cung cấp cho bạn một mức giá tốt với vận chuyển nhanh chóng!Cảm ơn! Kích thước trẻ em: 4t / 100: Vừa 88-105cm (Chiều cao) 6t / 110: Vừa 105-115cm (Chiều cao) 8t / 120: Vừa vặn 116-125cm (Chiều cao) 10t / 130: Vừa vặn 125-135cm (Chiều cao) 12t / 140: Phù hợp135-145cm (Chiều cao) So sánh kích thước chi tiết với của bạn, vui lòng cho phép chênh lệch 1-2CM do đo lường thủ công, cảm ơn Lưu ý: Do sự khác biệt giữa các màn hình khác nhau, hình ảnh có thể không phản ánh màu sắc thực tế của sản phẩm. Chúng tôi đảm bảo mẫu mã giống như trong hình, nhưng mỗi người cho kết quả khác nhau. Cảm ơn bạn! Mặt hàng Bao gồm (không bao gồm Dép) 1x đồ ngủ Giá sản phẩm trên Tiki đã bao gồm thuế theo luật hiện hành. Bên cạnh đó, tuỳ vào loại sản phẩm, hình thức và địa chỉ giao hàng mà có thể phát sinh thêm chi phí khác như phí vận chuyển, phụ phí hàng cồng kềnh, thuế nhập khẩu (đối với đơn hàng giao từ nước ngoài có giá trị trên 1 triệu đồng).....",
        "images_url": [
            "https://salt.tikicdn.com/media/catalog/product/f5/15/2228f38cf84d1b8451bb49e2c4537081.png"
        ]
    },
    {
        "id": 184912945,
        "name": "Trẻ Em Mùa Đông Charmander Động Vật Đồ Ngủ Trẻ Em Phim Hoạt Hình Quần Áo Ngủ Kigurumi Onesies Cho Trẻ Em Trai Cô Gái Chăn Ngủ Bé Trang Phục",
        "url_key": "tre-em-mua-dong-charmander-dong-vat-do-ngu-tre-em-phim-hoat-hinh-quan-ao-ngu-kigurumi-onesies-cho-tre-em-trai-co-gai-chan-ngu-be-trang-phuc-p184912945",
        "price": 350000,
        "description": "Kích thước là unisex, vì vậy bất kể bạn là nam hay nữ, bạn đều có thể mặc nó, chúng tôi cũng đề nghị bạn có thể sử dụng làm đồ ngủ cặp đôi, bạn có thể phối hợp nó, như đường may màu xanh và hồng, ma quỷ và dơi, Vân vân Có khóa kéo quanh hông, rất dễ dàng đi phòng tắm; Xin vui lòng cho tôi biết nếu bạn muốn nhiều hơn, chúng tôi sẽ cung cấp cho bạn một mức giá tốt với vận chuyển nhanh chóng!Cảm ơn! Kích thước trẻ em: 4t / 100: Vừa 88-105cm (Chiều cao) 6t / 110: Vừa 105-115cm (Chiều cao) 8t / 120: Vừa vặn 116-125cm (Chiều cao) 10t / 130: Vừa vặn 125-135cm (Chiều cao) 12t / 140: Phù hợp135-145cm (Chiều cao) So sánh kích thước chi tiết với của bạn, vui lòng cho phép chênh lệch 1-2CM do đo lường thủ công, cảm ơn Lưu ý: Do sự khác biệt giữa các màn hình khác nhau, hình ảnh có thể không phản ánh màu sắc thực tế của sản phẩm. Chúng tôi đảm bảo mẫu mã giống như trong hình, nhưng mỗi người cho kết quả khác nhau. Cảm ơn bạn! Mặt hàng Bao gồm (không bao gồm Dép) 1x đồ ngủ Giá sản phẩm trên Tiki đã bao gồm thuế theo luật hiện hành. Bên cạnh đó, tuỳ vào loại sản phẩm, hình thức và địa chỉ giao hàng mà có thể phát sinh thêm chi phí khác như phí vận chuyển, phụ phí hàng cồng kềnh, thuế nhập khẩu (đối với đơn hàng giao từ nước ngoài có giá trị trên 1 triệu đồng).....",
        "images_url": [
            "https://salt.tikicdn.com/media/catalog/product/f5/15/2228f38cf84d1b8451bb49e2c4537081.png"
        ]
    },
    {
        "id": 55973986,
        "name": "Cuddly Soft Plush Blanket Teething Security Tag Baby Safety Blanket",
        "url_key": "cuddly-soft-plush-blanket-teething-security-tag-baby-safety-blanket-p55973986",
        "price": 211000,
        "description": "Package Includes: 1 Piece Baby Blanket Note: e allow 1-3cm error due to manual measurement. Please make sure you do not mind before you bid. colors may have different as the difference display, please understand. Giá sản phẩm trên Tiki đã bao gồm thuế theo luật hiện hành. Bên cạnh đó, tuỳ vào loại sản phẩm, hình thức và địa chỉ giao hàng mà có thể phát sinh thêm chi phí khác như phí vận chuyển, phụ phí hàng cồng kềnh, thuế nhập khẩu (đối với đơn hàng giao từ nước ngoài có giá trị trên 1 triệu đồng).....",
        "images_url": [
            "https://salt.tikicdn.com/ts/product/d3/6d/37/67167680714d2d525e09342416317b5a.jpg",
            "https://salt.tikicdn.com/ts/product/03/cb/97/b2f4af454ec52034c1d01b83b7de1781.jpg",
            "https://salt.tikicdn.com/ts/product/da/10/4f/9796ab4a9226ae989d5ffdd1dc4dcf5f.jpg",
            "https://salt.tikicdn.com/ts/product/36/fb/45/4968d09047fd1234b24855aca24018c1.jpg",
            "https://salt.tikicdn.com/ts/product/32/dd/7c/0d66e98ceb890e1088858122ac900eb6.jpg",
            "https://salt.tikicdn.com/ts/product/9d/25/06/7e84840b837bf7e894cc3dca4bd21b7d.jpg"
        ]
    },
    {
        "id": 124668221,
        "name": "2021 Mới Thời Trang Cho Bé Sơ Sinh Phụ Kiện Bé Gái Quần Áo Bé Trai Bebe Jumpsuit Cách Mặc Quần Áo Cho Trẻ Sơ Sinh Chắc Chắn Chăn Cho Bé Sơ Sinh",
        "url_key": "2021-moi-thoi-trang-cho-be-so-sinh-phu-kien-be-gai-quan-ao-be-trai-bebe-jumpsuit-cach-mac-quan-ao-cho-tre-so-sinh-chac-chan-chan-cho-be-so-sinh-p124668221",
        "price": 558348,
        "description": "Tuổi Phạm vi:0-6M Tuổi Phạm vi:7-12M giới tính:Unisex nguồn gốc:CN (Nguồn Gốc) Chất liệu:Polar Fleece vải Số mô hình:Baby Blanket Loại mô hình:Rắn Nhóm tuổi:Babies Is_customized:Không Color:Pink White Khaki Purple Size:One Size Suitable For Season:Spring, autumn, winter Suitable For Age:0-12 Month Baby Girl Clothes:Baby Boy Clothes Place of Origin:Guangdong, China (Mainland) Infant Clothing:Newborn Blanket Infant Rompers:Baby Rompers Material:Polar Fleece Fabric Giá sản phẩm trên Tiki đã bao gồm thuế theo luật hiện hành. Bên cạnh đó, tuỳ vào loại sản phẩm, hình thức và địa chỉ giao hàng mà có thể phát sinh thêm chi phí khác như phí vận chuyển, phụ phí hàng cồng kềnh, thuế nhập khẩu (đối với đơn hàng giao từ nước ngoài có giá trị trên 1 triệu đồng).....",
        "images_url": [
            "https://salt.tikicdn.com/ts/product/12/fd/88/a010cd613df436ccd28967b82f440857.jpg",
            "https://salt.tikicdn.com/ts/product/2c/31/93/54257ac908ebf8b037ecdb50fdc96b6e.jpg",
            "https://salt.tikicdn.com/ts/product/51/90/44/6bad22ec9a3a4d3543b21472d1b42b19.jpg",
            "https://salt.tikicdn.com/ts/product/49/ce/ef/95b96cf26a4f89450c05edf54433243d.jpg",
            "https://salt.tikicdn.com/ts/product/8f/60/b8/037f433920de98ed9679aeaffdc17805.jpg",
            "https://salt.tikicdn.com/ts/product/8c/7c/56/7e9d141e279d79ebba0138676bb55f7e.jpg"
        ]
    },
    {
        "id": 124374366,
        "name": "Mềm Mại Cho Bé Sơ Sinh Bọc Chăn Túi Ngủ Cho Bé Bao Da Cho Trẻ Sơ Sinh Sleepsack Cotton Dày Ủ Kén Cho Bé 0-9 tháng",
        "url_key": "mem-mai-cho-be-so-sinh-boc-chan-tui-ngu-cho-be-bao-da-cho-tre-so-sinh-sleepsack-cotton-day-u-ken-cho-be-0-9-thang-p124374366",
        "price": 635145,
        "description": "Chất liệu:COTTON nguồn gốc:CN (Nguồn Gốc) mùa:Mùa đông giới tính:Bé Unisex Tuổi Phạm vi:0-6M Loại mô hình:Hình Hoạt Hình Tên bộ phận:baby cổ áo:Đội mũ trùm đầu Loại đóng cửa:Đơn ngực Loại sản phẩm:rompers Sleeve Length (cm):Đầy đủ Số mô hình:cotton Giá sản phẩm trên Tiki đã bao gồm thuế theo luật hiện hành. Bên cạnh đó, tuỳ vào loại sản phẩm, hình thức và địa chỉ giao hàng mà có thể phát sinh thêm chi phí khác như phí vận chuyển, phụ phí hàng cồng kềnh, thuế nhập khẩu (đối với đơn hàng giao từ nước ngoài có giá trị trên 1 triệu đồng).....",
        "images_url": [
            "https://salt.tikicdn.com/ts/product/42/26/c4/bbc08f6d46f016d9ce3255a7fa7183ab.jpg",
            "https://salt.tikicdn.com/ts/product/f0/7e/ff/41aa819307b7194f3e4740375bcc9ced.jpg",
            "https://salt.tikicdn.com/ts/product/ab/ef/86/4e8c9dc99ca3f38e06ef0ff5964ea40e.jpg",
            "https://salt.tikicdn.com/ts/product/be/90/7f/2e43f5949a5b624480be04e5a8208782.jpg",
            "https://salt.tikicdn.com/ts/product/26/2d/87/a559c6613707438ce6c42ec9d2174581.jpg",
            "https://salt.tikicdn.com/ts/product/61/c6/eb/7b23d11025e42e393668300e64937a6d.jpg"
        ]
    },
    {
        "id": 124349551,
        "name": "Bé Sơ Sinh Trang Phục Áo Liền Quần Onesie Mùa Đông Trẻ Sơ Sinh Quần Áo Ropa Bebe Mềm Bé Gái Bé Trai Rompers Dễ Thương Ong Dép Nỉ Cho Bé Bộ Trang Phục",
        "url_key": "be-so-sinh-trang-phuc-ao-lien-quan-onesie-mua-dong-tre-so-sinh-quan-ao-ropa-bebe-mem-be-gai-be-trai-rompers-de-thuong-ong-dep-ni-cho-be-bo-trang-phuc-p124349551",
        "price": 754446,
        "description": "Chất liệu:COTTON Chất liệu:Len nguồn gốc:CN (Nguồn Gốc) mùa:Mùa đông giới tính:Bé Unisex Tuổi Phạm vi:0-6M Tuổi Phạm vi:7-12M Tuổi Phạm vi:13-24M Tuổi Phạm vi:25-36M Loại mô hình:In Tên bộ phận:baby cổ áo:Đội mũ trùm đầu Loại đóng cửa:zipper Loại sản phẩm:rompers Sleeve Length (cm):Đầy đủ Số mô hình:HAX Fit:Phù hợp với đúng kích thước, mất bình thường của bạn kích thước Thành phần nguyên liệu:Flannel people:Newborn, baby boy, baby girl, infant, children Season:Winter, Autumn, Spring Use:Home, Festival, Play, Sleeping Sale of method:Wholesale, Drop shipping, retail Giá sản phẩm trên Tiki đã bao gồm thuế theo luật hiện hành. Bên cạnh đó, tuỳ vào loại sản phẩm, hình thức và địa chỉ giao hàng mà có thể phát sinh thêm chi phí khác như phí vận chuyển, phụ phí hàng cồng kềnh, thuế nhập khẩu (đối với đơn hàng giao từ nước ngoài có giá trị trên 1 triệu đồng).....",
        "images_url": [
            "https://salt.tikicdn.com/ts/product/13/fe/00/78937b974d79f0e70519764cbea2125a.jpg",
            "https://salt.tikicdn.com/ts/product/ae/8f/13/2e7c93252b17abab55dbf2942c68514c.jpg",
            "https://salt.tikicdn.com/ts/product/58/a5/2f/c3b40af36eb3b4a91f1f4cc101306a22.jpg",
            "https://salt.tikicdn.com/ts/product/f5/92/ca/87bd7e15109948840d16f54486032d83.jpg",
            "https://salt.tikicdn.com/ts/product/44/c1/43/b05124f8f2b1bef451e63ba179359b68.jpg",
            "https://salt.tikicdn.com/ts/product/a7/e6/02/45a33801b7f9455701f17af41e10c205.jpg"
        ]
    }
]